{
  "Color": "rgb(244, 55, 244)", 
  "Point": [
    {
      "Date": 20060803, 
      "Value" : 0.700000
    },
    {
      "Date": 20060821, 
      "Value" : 0.350000
    },
    {
      "Date": 20070618, 
      "Value" : 3.240000
    },
    {
      "Date": 20070711, 
      "Value" : 1.980000
    },
    {
      "Date": 20071010, 
      "Value" : 3.680000
    },
    {
      "Date": 20071128, 
      "Value" : 2.260000
    },
    {
      "Date": 20080117, 
      "Value" : 3.550000
    },
    {
      "Date": 20080201, 
      "Value" : 2.330000
    },
    {
      "Date": 20080303, 
      "Value" : 3.730000
    },
    {
      "Date": 20080422, 
      "Value" : 1.180000
    },
    {
      "Date": 20080512, 
      "Value" : 2.190000
    },
    {
      "Date": 20080703, 
      "Value" : 0.630000
    },
    {
      "Date": 20080723, 
      "Value" : 1.130000
    },
    {
      "Date": 20081017, 
      "Value" : -0.110000
    },
    {
      "Date": 20081209, 
      "Value" : 0.430000
    },
    {
      "Date": 20081231, 
      "Value" : 0.120000
    },
    {
      "Date": 20091116, 
      "Value" : 2.540000
    },
    {
      "Date": 20091222, 
      "Value" : 1.890000
    },
    {
      "Date": 20100118, 
      "Value" : 2.740000
    },
    {
      "Date": 20100208, 
      "Value" : 1.850000
    },
    {
      "Date": 20100506, 
      "Value" : 3.700000
    },
    {
      "Date": 20100702, 
      "Value" : 2.050000
    },
    {
      "Date": 20101111, 
      "Value" : 11.050000
    },
    {
      "Date": 20110131, 
      "Value" : 6.260000
    },
    {
      "Date": 20110329, 
      "Value" : 8.830000
    },
    {
      "Date": 20111227, 
      "Value" : 2.260000
    },
    {
      "Date": 20120319, 
      "Value" : 4.160000
    },
    {
      "Date": 20120424, 
      "Value" : 2.530000
    },
    {
      "Date": 20120531, 
      "Value" : 3.540000
    },
    {
      "Date": 20121204, 
      "Value" : 1.060000
    },
    {
      "Date": 20130118, 
      "Value" : 2.290000
    },
    {
      "Date": 20130408, 
      "Value" : 1.390000
    },
    {
      "Date": 20130527, 
      "Value" : 2.840000
    },
    {
      "Date": 20130628, 
      "Value" : 1.660000
    },
    {
      "Date": 20130909, 
      "Value" : 3.040000
    },
    {
      "Date": 20131021, 
      "Value" : 2.560000
    },
    {
      "Date": 20131105, 
      "Value" : 3.240000
    },
    {
      "Date": 20131226, 
      "Value" : 2.350000
    },
    {
      "Date": 20140307, 
      "Value" : 3.980000
    },
    {
      "Date": 20140331, 
      "Value" : 2.980000
    },
    {
      "Date": 20140417, 
      "Value" : 3.470000
    },
    {
      "Date": 20140523, 
      "Value" : 2.930000
    },
    {
      "Date": 20140915, 
      "Value" : 4.490000
    },
    {
      "Date": 20141117, 
      "Value" : 3.800000
    },
    {
      "Date": 20141215, 
      "Value" : 4.920000
    },
    {
      "Date": 20150115, 
      "Value" : 4.090000
    },
    {
      "Date": 20150605, 
      "Value" : 10.380000
    },
    {
      "Date": 20150915, 
      "Value" : 2.750000
    },
    {
      "Date": 20151221, 
      "Value" : 6.580000
    },
    {
      "Date": 20160304, 
      "Value" : 3.280000
    },
    {
      "Date": 20160628, 
      "Value" : 7.800000
    },
    {
      "Date": 20160801, 
      "Value" : 5.770000
    },
    {
      "Date": 20160831, 
      "Value" : 6.640000
    },
    {
      "Date": 20160929, 
      "Value" : 5.910000
    },
    {
      "Date": 20161021, 
      "Value" : 6.490000
    },
    {
      "Date": 20161214, 
      "Value" : 5.030000
    },
    {
      "Date": 20170912, 
      "Value" : 11.660000
    },
    {
      "Date": 20171017, 
      "Value" : 8.910000
    },
    {
      "Date": 20171122, 
      "Value" : 10.980000
    },
    {
      "Date": 20171218, 
      "Value" : 9.030000
    },
    {
      "Date": 20180112, 
      "Value" : 10.310000
    },
    {
      "Date": 20180209, 
      "Value" : 6.760000
    },
    {
      "Date": 20180314, 
      "Value" : 9.190000
    },
    {
      "Date": 20180626, 
      "Value" : 5.330000
    },
    {
      "Date": 20180724, 
      "Value" : 6.860000
    },
    {
      "Date": 20181019, 
      "Value" : 3.430000
    },
    {
      "Date": 20181203, 
      "Value" : 5.060000
    },
    {
      "Date": 20181225, 
      "Value" : 4.050000
    },
    {
      "Date": 20190612, 
      "Value" : 8.550000
    },
    {
      "Date": 20190815, 
      "Value" : 5.520000
    },
    {
      "Date": 20190923, 
      "Value" : 6.680000
    },
    {
      "Date": 20191101, 
      "Value" : 5.580000
    },
    {
      "Date": 20200225, 
      "Value" : 14.380000
    },
    {
      "Date": 20200428, 
      "Value" : 8.310000
    },
    {
      "Date": 20200714, 
      "Value" : 12.590000
    },
    {
      "Date": 20200814, 
      "Value" : 10.170000
    },
    {
      "Date": 20201110, 
      "Value" : 14.580000
    },
    {
      "Date": 20201214, 
      "Value" : 12.280000
    },
    {
      "Date": 20210121, 
      "Value" : 17.480000
    },
    {
      "Date": 20210205, 
      "Value" : 12.390000
    },
    {
      "Date": 20210326, 
      "Value" : 15.080000
    },
    {
      "Date": 20210617, 
      "Value" : 11.340000
    },
    {
      "Date": 20210907, 
      "Value" : 16.270000
    },
    {
      "Date": 20211012, 
      "Value" : 12.190000
    },
    {
      "Date": 20211214, 
      "Value" : 22.350000
    },
    {
      "Date": 20220128, 
      "Value" : 14.690000
    },
    {
      "Date": 20220301, 
      "Value" : 16.740000
    },
    {
      "Date": 20220412, 
      "Value" : 12.310000
    },
    {
      "Date": 20220629, 
      "Value" : 27.639999
    },
    {
      "Date": 20220804, 
      "Value" : 20.080000
    },
    {
      "Date": 20220819, 
      "Value" : 25.520000
    },
    {
      "Date": 20221121, 
      "Value" : 17.440001
    },
    {
      "Date": 20221202, 
      "Value" : 19.530001
    },
    {
      "Date": 20221223, 
      "Value" : 16.480000
    },
    {
      "Date": 20230131, 
      "Value" : 22.570000
    },
    {
      "Date": 20230320, 
      "Value" : 18.719999
    },
    {
      "Date": 20230418, 
      "Value" : 20.590000
    },
    {
      "Date": 20230515, 
      "Value" : 17.709999
    }
  ]
}