{
  "Color": "rgb(244, 55, 244)", 
  "Point": [
    {
      "Date": 20070328, 
      "Value" : 7.670000
    },
    {
      "Date": 20070619, 
      "Value" : 10.800000
    },
    {
      "Date": 20070713, 
      "Value" : 8.730000
    },
    {
      "Date": 20071011, 
      "Value" : 18.209999
    },
    {
      "Date": 20071122, 
      "Value" : 13.800000
    },
    {
      "Date": 20080125, 
      "Value" : 20.040001
    },
    {
      "Date": 20080422, 
      "Value" : 11.020000
    },
    {
      "Date": 20080513, 
      "Value" : 17.070000
    },
    {
      "Date": 20080619, 
      "Value" : 10.040000
    },
    {
      "Date": 20080804, 
      "Value" : 14.020000
    },
    {
      "Date": 20081107, 
      "Value" : 9.100000
    },
    {
      "Date": 20090416, 
      "Value" : 17.900000
    },
    {
      "Date": 20090615, 
      "Value" : 13.160000
    },
    {
      "Date": 20090805, 
      "Value" : 17.920000
    },
    {
      "Date": 20090929, 
      "Value" : 11.990000
    },
    {
      "Date": 20091120, 
      "Value" : 16.250000
    },
    {
      "Date": 20091223, 
      "Value" : 13.430000
    },
    {
      "Date": 20100120, 
      "Value" : 15.240000
    },
    {
      "Date": 20100316, 
      "Value" : 12.600000
    },
    {
      "Date": 20100412, 
      "Value" : 14.990000
    },
    {
      "Date": 20100702, 
      "Value" : 8.320000
    },
    {
      "Date": 20100819, 
      "Value" : 10.960000
    },
    {
      "Date": 20100903, 
      "Value" : 9.720000
    },
    {
      "Date": 20101101, 
      "Value" : 14.720000
    },
    {
      "Date": 20101123, 
      "Value" : 11.820000
    },
    {
      "Date": 20110217, 
      "Value" : 18.820000
    },
    {
      "Date": 20110623, 
      "Value" : 11.520000
    },
    {
      "Date": 20110707, 
      "Value" : 13.100000
    },
    {
      "Date": 20111228, 
      "Value" : 5.700000
    },
    {
      "Date": 20120305, 
      "Value" : 7.900000
    },
    {
      "Date": 20120410, 
      "Value" : 6.150000
    },
    {
      "Date": 20120529, 
      "Value" : 7.580000
    },
    {
      "Date": 20120726, 
      "Value" : 5.960000
    },
    {
      "Date": 20120809, 
      "Value" : 6.320000
    },
    {
      "Date": 20120926, 
      "Value" : 5.170000
    },
    {
      "Date": 20121023, 
      "Value" : 5.750000
    },
    {
      "Date": 20121203, 
      "Value" : 4.580000
    },
    {
      "Date": 20130208, 
      "Value" : 5.760000
    },
    {
      "Date": 20130502, 
      "Value" : 4.650000
    },
    {
      "Date": 20130529, 
      "Value" : 5.280000
    },
    {
      "Date": 20130709, 
      "Value" : 3.370000
    },
    {
      "Date": 20131022, 
      "Value" : 5.010000
    },
    {
      "Date": 20140114, 
      "Value" : 3.620000
    },
    {
      "Date": 20140219, 
      "Value" : 4.340000
    },
    {
      "Date": 20140314, 
      "Value" : 3.880000
    },
    {
      "Date": 20140513, 
      "Value" : 4.740000
    },
    {
      "Date": 20140612, 
      "Value" : 4.180000
    },
    {
      "Date": 20141127, 
      "Value" : 9.060000
    },
    {
      "Date": 20150119, 
      "Value" : 6.480000
    },
    {
      "Date": 20150610, 
      "Value" : 14.930000
    },
    {
      "Date": 20150708, 
      "Value" : 6.080000
    },
    {
      "Date": 20150817, 
      "Value" : 10.930000
    },
    {
      "Date": 20150915, 
      "Value" : 5.680000
    },
    {
      "Date": 20151126, 
      "Value" : 8.890000
    },
    {
      "Date": 20151214, 
      "Value" : 7.230000
    },
    {
      "Date": 20151231, 
      "Value" : 8.410000
    },
    {
      "Date": 20160229, 
      "Value" : 5.460000
    },
    {
      "Date": 20160418, 
      "Value" : 7.060000
    },
    {
      "Date": 20160615, 
      "Value" : 5.950000
    },
    {
      "Date": 20161109, 
      "Value" : 14.870000
    },
    {
      "Date": 20161213, 
      "Value" : 10.830000
    },
    {
      "Date": 20170105, 
      "Value" : 13.700000
    },
    {
      "Date": 20180809, 
      "Value" : 1.450000
    },
    {
      "Date": 20180906, 
      "Value" : 1.900000
    },
    {
      "Date": 20181019, 
      "Value" : 1.410000
    },
    {
      "Date": 20181115, 
      "Value" : 2.400000
    },
    {
      "Date": 20190201, 
      "Value" : 1.530000
    },
    {
      "Date": 20190326, 
      "Value" : 3.780000
    },
    {
      "Date": 20190531, 
      "Value" : 2.110000
    },
    {
      "Date": 20190702, 
      "Value" : 2.410000
    },
    {
      "Date": 20190808, 
      "Value" : 1.660000
    },
    {
      "Date": 20190911, 
      "Value" : 2.140000
    },
    {
      "Date": 20190926, 
      "Value" : 1.880000
    },
    {
      "Date": 20191018, 
      "Value" : 2.170000
    },
    {
      "Date": 20191203, 
      "Value" : 1.820000
    },
    {
      "Date": 20200109, 
      "Value" : 2.040000
    },
    {
      "Date": 20200528, 
      "Value" : 1.180000
    },
    {
      "Date": 20200921, 
      "Value" : 2.340000
    },
    {
      "Date": 20201106, 
      "Value" : 2.020000
    },
    {
      "Date": 20201216, 
      "Value" : 2.380000
    },
    {
      "Date": 20210226, 
      "Value" : 1.850000
    },
    {
      "Date": 20210617, 
      "Value" : 3.340000
    },
    {
      "Date": 20210714, 
      "Value" : 2.520000
    },
    {
      "Date": 20210831, 
      "Value" : 3.840000
    },
    {
      "Date": 20220215, 
      "Value" : 2.220000
    },
    {
      "Date": 20220413, 
      "Value" : 2.640000
    },
    {
      "Date": 20220614, 
      "Value" : 1.760000
    },
    {
      "Date": 20221010, 
      "Value" : 2.800000
    },
    {
      "Date": 20221108, 
      "Value" : 2.420000
    },
    {
      "Date": 20230413, 
      "Value" : 5.450000
    },
    {
      "Date": 20230524, 
      "Value" : 3.980000
    },
    {
      "Date": 20230615, 
      "Value" : 5.640000
    },
    {
      "Date": 20230926, 
      "Value" : 3.050000
    },
    {
      "Date": 20231107, 
      "Value" : 4.800000
    },
    {
      "Date": 20240206, 
      "Value" : 2.650000
    }
  ]
}