{
  "Color": "rgb(244, 55, 244)", 
  "Point": [
    {
      "Date": 20101115, 
      "Value" : 9.510000
    },
    {
      "Date": 20101116, 
      "Value" : 11.220000
    },
    {
      "Date": 20110125, 
      "Value" : 7.510000
    },
    {
      "Date": 20110309, 
      "Value" : 8.590000
    },
    {
      "Date": 20110620, 
      "Value" : 6.610000
    },
    {
      "Date": 20110707, 
      "Value" : 7.380000
    },
    {
      "Date": 20110819, 
      "Value" : 6.040000
    },
    {
      "Date": 20111028, 
      "Value" : 7.810000
    },
    {
      "Date": 20120106, 
      "Value" : 4.570000
    },
    {
      "Date": 20120426, 
      "Value" : 7.140000
    },
    {
      "Date": 20121204, 
      "Value" : 4.170000
    },
    {
      "Date": 20130325, 
      "Value" : 6.840000
    },
    {
      "Date": 20130502, 
      "Value" : 5.640000
    },
    {
      "Date": 20130603, 
      "Value" : 6.280000
    },
    {
      "Date": 20130628, 
      "Value" : 4.570000
    },
    {
      "Date": 20130912, 
      "Value" : 5.780000
    },
    {
      "Date": 20131114, 
      "Value" : 4.690000
    },
    {
      "Date": 20131204, 
      "Value" : 5.670000
    },
    {
      "Date": 20140120, 
      "Value" : 5.140000
    },
    {
      "Date": 20140217, 
      "Value" : 5.690000
    },
    {
      "Date": 20140312, 
      "Value" : 4.980000
    },
    {
      "Date": 20140514, 
      "Value" : 5.540000
    },
    {
      "Date": 20140625, 
      "Value" : 5.140000
    },
    {
      "Date": 20141209, 
      "Value" : 15.430000
    },
    {
      "Date": 20150206, 
      "Value" : 10.460000
    },
    {
      "Date": 20150526, 
      "Value" : 22.040001
    },
    {
      "Date": 20150915, 
      "Value" : 7.270000
    },
    {
      "Date": 20151117, 
      "Value" : 14.770000
    },
    {
      "Date": 20160229, 
      "Value" : 7.300000
    },
    {
      "Date": 20160704, 
      "Value" : 13.670000
    },
    {
      "Date": 20160926, 
      "Value" : 10.770000
    },
    {
      "Date": 20161116, 
      "Value" : 11.930000
    },
    {
      "Date": 20170524, 
      "Value" : 7.070000
    },
    {
      "Date": 20170901, 
      "Value" : 10.030000
    },
    {
      "Date": 20171227, 
      "Value" : 7.430000
    },
    {
      "Date": 20180126, 
      "Value" : 8.210000
    },
    {
      "Date": 20180328, 
      "Value" : 6.030000
    },
    {
      "Date": 20180507, 
      "Value" : 7.000000
    },
    {
      "Date": 20181019, 
      "Value" : 4.310000
    },
    {
      "Date": 20181122, 
      "Value" : 5.800000
    },
    {
      "Date": 20181227, 
      "Value" : 5.090000
    },
    {
      "Date": 20190403, 
      "Value" : 8.630000
    },
    {
      "Date": 20190610, 
      "Value" : 6.360000
    },
    {
      "Date": 20190719, 
      "Value" : 7.440000
    },
    {
      "Date": 20190815, 
      "Value" : 6.310000
    },
    {
      "Date": 20190917, 
      "Value" : 7.230000
    },
    {
      "Date": 20191121, 
      "Value" : 6.260000
    },
    {
      "Date": 20200108, 
      "Value" : 7.290000
    },
    {
      "Date": 20200204, 
      "Value" : 5.570000
    },
    {
      "Date": 20200310, 
      "Value" : 7.130000
    },
    {
      "Date": 20200616, 
      "Value" : 5.600000
    },
    {
      "Date": 20200713, 
      "Value" : 9.520000
    },
    {
      "Date": 20210511, 
      "Value" : 6.170000
    },
    {
      "Date": 20210528, 
      "Value" : 6.760000
    },
    {
      "Date": 20210806, 
      "Value" : 5.890000
    },
    {
      "Date": 20210910, 
      "Value" : 6.800000
    },
    {
      "Date": 20211102, 
      "Value" : 5.870000
    },
    {
      "Date": 20220105, 
      "Value" : 6.310000
    },
    {
      "Date": 20220427, 
      "Value" : 4.380000
    },
    {
      "Date": 20220617, 
      "Value" : 5.660000
    },
    {
      "Date": 20220804, 
      "Value" : 4.940000
    },
    {
      "Date": 20220830, 
      "Value" : 6.060000
    },
    {
      "Date": 20221010, 
      "Value" : 4.760000
    },
    {
      "Date": 20221206, 
      "Value" : 5.500000
    },
    {
      "Date": 20221229, 
      "Value" : 5.000000
    },
    {
      "Date": 20230120, 
      "Value" : 5.970000
    },
    {
      "Date": 20230316, 
      "Value" : 5.420000
    },
    {
      "Date": 20230410, 
      "Value" : 5.750000
    },
    {
      "Date": 20230427, 
      "Value" : 5.280000
    },
    {
      "Date": 20230829, 
      "Value" : 6.970000
    },
    {
      "Date": 20231023, 
      "Value" : 5.320000
    },
    {
      "Date": 20231115, 
      "Value" : 5.750000
    },
    {
      "Date": 20240205, 
      "Value" : 4.350000
    },
    {
      "Date": 20240301, 
      "Value" : 5.340000
    },
    {
      "Date": 20240416, 
      "Value" : 4.580000
    },
    {
      "Date": 20240515, 
      "Value" : 5.210000
    },
    {
      "Date": 20240709, 
      "Value" : 4.400000
    },
    {
      "Date": 20241108, 
      "Value" : 7.400000
    },
    {
      "Date": 20241127, 
      "Value" : 6.120000
    },
    {
      "Date": 20241212, 
      "Value" : 6.840000
    },
    {
      "Date": 20250113, 
      "Value" : 5.700000
    },
    {
      "Date": 20250217, 
      "Value" : 6.310000
    },
    {
      "Date": 20250409, 
      "Value" : 5.290000
    }
  ]
}