{
  "Color": "rgb(244, 55, 244)", 
  "Point": [
    {
      "Date": 20180115, 
      "Value" : 11.260000
    },
    {
      "Date": 20180312, 
      "Value" : 59.270000
    },
    {
      "Date": 20180502, 
      "Value" : 32.959999
    },
    {
      "Date": 20180523, 
      "Value" : 40.889999
    },
    {
      "Date": 20180620, 
      "Value" : 23.620001
    },
    {
      "Date": 20180725, 
      "Value" : 33.599998
    },
    {
      "Date": 20181019, 
      "Value" : 13.160000
    },
    {
      "Date": 20181203, 
      "Value" : 26.020000
    },
    {
      "Date": 20190104, 
      "Value" : 19.670000
    },
    {
      "Date": 20190225, 
      "Value" : 32.849998
    },
    {
      "Date": 20190812, 
      "Value" : 16.250000
    },
    {
      "Date": 20200306, 
      "Value" : 39.730000
    },
    {
      "Date": 20200330, 
      "Value" : 21.290001
    },
    {
      "Date": 20200714, 
      "Value" : 40.889999
    },
    {
      "Date": 20200812, 
      "Value" : 28.230000
    },
    {
      "Date": 20200903, 
      "Value" : 34.330002
    },
    {
      "Date": 20200915, 
      "Value" : 29.910000
    },
    {
      "Date": 20201124, 
      "Value" : 39.130001
    },
    {
      "Date": 20210111, 
      "Value" : 31.250000
    },
    {
      "Date": 20210218, 
      "Value" : 39.959999
    },
    {
      "Date": 20210316, 
      "Value" : 29.430000
    },
    {
      "Date": 20210525, 
      "Value" : 42.009998
    },
    {
      "Date": 20211101, 
      "Value" : 27.639999
    },
    {
      "Date": 20220112, 
      "Value" : 32.570000
    },
    {
      "Date": 20220506, 
      "Value" : 17.049999
    },
    {
      "Date": 20220822, 
      "Value" : 24.540001
    },
    {
      "Date": 20221228, 
      "Value" : 14.970000
    },
    {
      "Date": 20230330, 
      "Value" : 19.719999
    },
    {
      "Date": 20240205, 
      "Value" : 11.850000
    },
    {
      "Date": 20240307, 
      "Value" : 17.150000
    },
    {
      "Date": 20240828, 
      "Value" : 10.290000
    },
    {
      "Date": 20241008, 
      "Value" : 15.050000
    }
  ]
}