{
  "Color": "rgb(244, 55, 244)", 
  "Point": [
    {
      "Date": 20160309, 
      "Value" : 3.400000
    },
    {
      "Date": 20160708, 
      "Value" : 32.900002
    },
    {
      "Date": 20160801, 
      "Value" : 23.700001
    },
    {
      "Date": 20160825, 
      "Value" : 32.209999
    },
    {
      "Date": 20160930, 
      "Value" : 24.510000
    },
    {
      "Date": 20161201, 
      "Value" : 41.099998
    },
    {
      "Date": 20170124, 
      "Value" : 22.900000
    },
    {
      "Date": 20170317, 
      "Value" : 27.090000
    },
    {
      "Date": 20180202, 
      "Value" : 9.670000
    },
    {
      "Date": 20180403, 
      "Value" : 15.280000
    },
    {
      "Date": 20180503, 
      "Value" : 12.040000
    },
    {
      "Date": 20180524, 
      "Value" : 16.340000
    },
    {
      "Date": 20180918, 
      "Value" : 8.340000
    },
    {
      "Date": 20181113, 
      "Value" : 10.970000
    },
    {
      "Date": 20190131, 
      "Value" : 7.890000
    },
    {
      "Date": 20190313, 
      "Value" : 11.420000
    },
    {
      "Date": 20190329, 
      "Value" : 9.660000
    },
    {
      "Date": 20190418, 
      "Value" : 11.430000
    },
    {
      "Date": 20190722, 
      "Value" : 7.380000
    },
    {
      "Date": 20190819, 
      "Value" : 8.760000
    },
    {
      "Date": 20190830, 
      "Value" : 7.580000
    },
    {
      "Date": 20200306, 
      "Value" : 14.840000
    },
    {
      "Date": 20200323, 
      "Value" : 10.990000
    },
    {
      "Date": 20200709, 
      "Value" : 15.880000
    },
    {
      "Date": 20201102, 
      "Value" : 21.070000
    },
    {
      "Date": 20210209, 
      "Value" : 9.120000
    },
    {
      "Date": 20210308, 
      "Value" : 15.660000
    },
    {
      "Date": 20210525, 
      "Value" : 10.030000
    },
    {
      "Date": 20210728, 
      "Value" : 10.080000
    },
    {
      "Date": 20210827, 
      "Value" : 20.549999
    },
    {
      "Date": 20211123, 
      "Value" : 17.500000
    },
    {
      "Date": 20220128, 
      "Value" : 11.120000
    },
    {
      "Date": 20220506, 
      "Value" : 7.910000
    },
    {
      "Date": 20220801, 
      "Value" : 15.690000
    },
    {
      "Date": 20220919, 
      "Value" : 9.130000
    }
  ]
}