{
  "Color": "rgb(244, 55, 244)", 
  "Point": [
    {
      "Date": 20170307, 
      "Value" : 34.180000
    },
    {
      "Date": 20180516, 
      "Value" : 131.300003
    },
    {
      "Date": 20180917, 
      "Value" : 72.500000
    },
    {
      "Date": 20180928, 
      "Value" : 88.550003
    },
    {
      "Date": 20190104, 
      "Value" : 53.400002
    },
    {
      "Date": 20190402, 
      "Value" : 98.949997
    },
    {
      "Date": 20190617, 
      "Value" : 67.230003
    },
    {
      "Date": 20190823, 
      "Value" : 90.750000
    },
    {
      "Date": 20200323, 
      "Value" : 60.599998
    },
    {
      "Date": 20200428, 
      "Value" : 66.800003
    },
    {
      "Date": 20200629, 
      "Value" : 58.060001
    },
    {
      "Date": 20200818, 
      "Value" : 72.089996
    },
    {
      "Date": 20201026, 
      "Value" : 57.799999
    },
    {
      "Date": 20210107, 
      "Value" : 91.970001
    },
    {
      "Date": 20210226, 
      "Value" : 67.690002
    },
    {
      "Date": 20210318, 
      "Value" : 88.580002
    },
    {
      "Date": 20210521, 
      "Value" : 64.820000
    },
    {
      "Date": 20210628, 
      "Value" : 98.070000
    },
    {
      "Date": 20211102, 
      "Value" : 41.900002
    },
    {
      "Date": 20211124, 
      "Value" : 48.380001
    },
    {
      "Date": 20220429, 
      "Value" : 22.950001
    },
    {
      "Date": 20220701, 
      "Value" : 29.500000
    },
    {
      "Date": 20221025, 
      "Value" : 16.709999
    },
    {
      "Date": 20230322, 
      "Value" : 29.900000
    },
    {
      "Date": 20230505, 
      "Value" : 20.280001
    }
  ]
}