{
  "Color": "rgb(244, 55, 244)", 
  "Point": [
    {
      "Date": 20180611, 
      "Value" : 9.640000
    },
    {
      "Date": 20190306, 
      "Value" : 44.990002
    },
    {
      "Date": 20190611, 
      "Value" : 28.430000
    },
    {
      "Date": 20190911, 
      "Value" : 38.000000
    },
    {
      "Date": 20191101, 
      "Value" : 30.959999
    },
    {
      "Date": 20200206, 
      "Value" : 87.339996
    },
    {
      "Date": 20200323, 
      "Value" : 51.290001
    },
    {
      "Date": 20200806, 
      "Value" : 114.120003
    },
    {
      "Date": 20200911, 
      "Value" : 94.940002
    },
    {
      "Date": 20201106, 
      "Value" : 145.979996
    },
    {
      "Date": 20201202, 
      "Value" : 124.519997
    },
    {
      "Date": 20210108, 
      "Value" : 229.179993
    },
    {
      "Date": 20210325, 
      "Value" : 148.660004
    },
    {
      "Date": 20210730, 
      "Value" : 316.649994
    },
    {
      "Date": 20210820, 
      "Value" : 261.260010
    },
    {
      "Date": 20211203, 
      "Value" : 377.649994
    },
    {
      "Date": 20220308, 
      "Value" : 239.330002
    },
    {
      "Date": 20220323, 
      "Value" : 283.750000
    },
    {
      "Date": 20220510, 
      "Value" : 191.619995
    },
    {
      "Date": 20220627, 
      "Value" : 307.079987
    },
    {
      "Date": 20220808, 
      "Value" : 264.880005
    },
    {
      "Date": 20220824, 
      "Value" : 312.649994
    },
    {
      "Date": 20221128, 
      "Value" : 193.580002
    },
    {
      "Date": 20221219, 
      "Value" : 232.520004
    },
    {
      "Date": 20230103, 
      "Value" : 205.639999
    },
    {
      "Date": 20230202, 
      "Value" : 260.070007
    },
    {
      "Date": 20230320, 
      "Value" : 198.020004
    },
    {
      "Date": 20230517, 
      "Value" : 236.649994
    },
    {
      "Date": 20230607, 
      "Value" : 199.419998
    },
    {
      "Date": 20230810, 
      "Value" : 246.300003
    },
    {
      "Date": 20240130, 
      "Value" : 135.369995
    },
    {
      "Date": 20240509, 
      "Value" : 210.509995
    },
    {
      "Date": 20240710, 
      "Value" : 173.050003
    }
  ]
}