{
  "Color": "rgb(244, 55, 244)", 
  "Point": [
    {
      "Date": 20220322, 
      "Value" : 28.360001
    },
    {
      "Date": 20221031, 
      "Value" : 12.910000
    },
    {
      "Date": 20221205, 
      "Value" : 15.710000
    },
    {
      "Date": 20221229, 
      "Value" : 13.120000
    },
    {
      "Date": 20230320, 
      "Value" : 17.420000
    },
    {
      "Date": 20230425, 
      "Value" : 13.590000
    },
    {
      "Date": 20230821, 
      "Value" : 25.500000
    }
  ]
}