{
  "Color": "rgb(244, 55, 244)", 
  "Point": [
    {
      "Date": 20230615, 
      "Value" : 68.300003
    },
    {
      "Date": 20230616, 
      "Value" : 74.540001
    },
    {
      "Date": 20230808, 
      "Value" : 55.799999
    },
    {
      "Date": 20230821, 
      "Value" : 64.050003
    },
    {
      "Date": 20231026, 
      "Value" : 48.320000
    },
    {
      "Date": 20231120, 
      "Value" : 53.279999
    },
    {
      "Date": 20231219, 
      "Value" : 46.810001
    }
  ]
}