{
  "Color": "rgb(244, 55, 244)", 
  "Point": [
    {
      "Date": 20060510, 
      "Value" : 2.240000
    },
    {
      "Date": 20060726, 
      "Value" : 3.360000
    },
    {
      "Date": 20060824, 
      "Value" : 2.870000
    },
    {
      "Date": 20061012, 
      "Value" : 3.410000
    },
    {
      "Date": 20061117, 
      "Value" : 2.700000
    },
    {
      "Date": 20070529, 
      "Value" : 10.080000
    },
    {
      "Date": 20070705, 
      "Value" : 5.850000
    },
    {
      "Date": 20070903, 
      "Value" : 11.170000
    },
    {
      "Date": 20071221, 
      "Value" : 6.630000
    },
    {
      "Date": 20080116, 
      "Value" : 9.050000
    },
    {
      "Date": 20080703, 
      "Value" : 3.150000
    },
    {
      "Date": 20080728, 
      "Value" : 3.860000
    },
    {
      "Date": 20081104, 
      "Value" : 1.860000
    },
    {
      "Date": 20090805, 
      "Value" : 5.480000
    },
    {
      "Date": 20090819, 
      "Value" : 4.060000
    },
    {
      "Date": 20091120, 
      "Value" : 6.800000
    },
    {
      "Date": 20100129, 
      "Value" : 5.460000
    },
    {
      "Date": 20100308, 
      "Value" : 6.680000
    },
    {
      "Date": 20100702, 
      "Value" : 3.780000
    },
    {
      "Date": 20100818, 
      "Value" : 5.450000
    },
    {
      "Date": 20100930, 
      "Value" : 4.560000
    },
    {
      "Date": 20110211, 
      "Value" : 8.170000
    },
    {
      "Date": 20110322, 
      "Value" : 6.790000
    },
    {
      "Date": 20110421, 
      "Value" : 7.860000
    },
    {
      "Date": 20120106, 
      "Value" : 3.640000
    },
    {
      "Date": 20120601, 
      "Value" : 5.210000
    },
    {
      "Date": 20120803, 
      "Value" : 3.810000
    },
    {
      "Date": 20120816, 
      "Value" : 5.010000
    },
    {
      "Date": 20121204, 
      "Value" : 3.610000
    },
    {
      "Date": 20130206, 
      "Value" : 4.810000
    },
    {
      "Date": 20130315, 
      "Value" : 4.120000
    },
    {
      "Date": 20130402, 
      "Value" : 4.700000
    },
    {
      "Date": 20130625, 
      "Value" : 3.320000
    },
    {
      "Date": 20131015, 
      "Value" : 4.340000
    },
    {
      "Date": 20140110, 
      "Value" : 3.470000
    },
    {
      "Date": 20140214, 
      "Value" : 4.060000
    },
    {
      "Date": 20140624, 
      "Value" : 3.400000
    },
    {
      "Date": 20141204, 
      "Value" : 6.270000
    },
    {
      "Date": 20141224, 
      "Value" : 5.070000
    },
    {
      "Date": 20150615, 
      "Value" : 16.430000
    },
    {
      "Date": 20150916, 
      "Value" : 5.940000
    },
    {
      "Date": 20151230, 
      "Value" : 11.500000
    },
    {
      "Date": 20160128, 
      "Value" : 5.630000
    },
    {
      "Date": 20170120, 
      "Value" : 15.140000
    },
    {
      "Date": 20170303, 
      "Value" : 10.640000
    },
    {
      "Date": 20170413, 
      "Value" : 14.360000
    },
    {
      "Date": 20170516, 
      "Value" : 9.150000
    },
    {
      "Date": 20170707, 
      "Value" : 11.520000
    },
    {
      "Date": 20170927, 
      "Value" : 9.650000
    },
    {
      "Date": 20171201, 
      "Value" : 12.170000
    },
    {
      "Date": 20180209, 
      "Value" : 7.620000
    },
    {
      "Date": 20180314, 
      "Value" : 11.230000
    },
    {
      "Date": 20181019, 
      "Value" : 6.050000
    },
    {
      "Date": 20181122, 
      "Value" : 7.520000
    },
    {
      "Date": 20181225, 
      "Value" : 6.220000
    },
    {
      "Date": 20190403, 
      "Value" : 9.210000
    },
    {
      "Date": 20191230, 
      "Value" : 6.090000
    },
    {
      "Date": 20200207, 
      "Value" : 12.200000
    },
    {
      "Date": 20201030, 
      "Value" : 4.840000
    },
    {
      "Date": 20201202, 
      "Value" : 5.600000
    },
    {
      "Date": 20210208, 
      "Value" : 4.620000
    },
    {
      "Date": 20210512, 
      "Value" : 7.250000
    },
    {
      "Date": 20210526, 
      "Value" : 6.270000
    },
    {
      "Date": 20210629, 
      "Value" : 8.610000
    },
    {
      "Date": 20210820, 
      "Value" : 6.190000
    },
    {
      "Date": 20211013, 
      "Value" : 8.720000
    },
    {
      "Date": 20211103, 
      "Value" : 7.110000
    },
    {
      "Date": 20211202, 
      "Value" : 11.630000
    },
    {
      "Date": 20220318, 
      "Value" : 7.160000
    },
    {
      "Date": 20220408, 
      "Value" : 8.800000
    },
    {
      "Date": 20220527, 
      "Value" : 6.300000
    },
    {
      "Date": 20220805, 
      "Value" : 9.500000
    },
    {
      "Date": 20221031, 
      "Value" : 6.170000
    },
    {
      "Date": 20221118, 
      "Value" : 6.720000
    },
    {
      "Date": 20221230, 
      "Value" : 5.680000
    },
    {
      "Date": 20230131, 
      "Value" : 7.220000
    },
    {
      "Date": 20230425, 
      "Value" : 5.880000
    },
    {
      "Date": 20230727, 
      "Value" : 10.910000
    }
  ]
}