{
  "Color": "rgb(244, 55, 244)", 
  "Point": [
    {
      "Date": 20060511, 
      "Value" : 0.980000
    },
    {
      "Date": 20060512, 
      "Value" : 0.710000
    },
    {
      "Date": 20070119, 
      "Value" : 4.930000
    },
    {
      "Date": 20070208, 
      "Value" : 3.830000
    },
    {
      "Date": 20070911, 
      "Value" : 12.800000
    },
    {
      "Date": 20071204, 
      "Value" : 4.570000
    },
    {
      "Date": 20080121, 
      "Value" : 9.360000
    },
    {
      "Date": 20080422, 
      "Value" : 2.030000
    },
    {
      "Date": 20080515, 
      "Value" : 5.280000
    },
    {
      "Date": 20080703, 
      "Value" : 1.900000
    },
    {
      "Date": 20080729, 
      "Value" : 3.560000
    },
    {
      "Date": 20081104, 
      "Value" : 0.060000
    },
    {
      "Date": 20100225, 
      "Value" : 8.390000
    },
    {
      "Date": 20100702, 
      "Value" : 3.480000
    },
    {
      "Date": 20101222, 
      "Value" : 12.050000
    },
    {
      "Date": 20110125, 
      "Value" : 7.350000
    },
    {
      "Date": 20110328, 
      "Value" : 10.500000
    },
    {
      "Date": 20110602, 
      "Value" : 6.860000
    },
    {
      "Date": 20110718, 
      "Value" : 9.640000
    },
    {
      "Date": 20120106, 
      "Value" : 4.180000
    },
    {
      "Date": 20130221, 
      "Value" : 9.730000
    },
    {
      "Date": 20130314, 
      "Value" : 8.180000
    },
    {
      "Date": 20130327, 
      "Value" : 9.480000
    },
    {
      "Date": 20130415, 
      "Value" : 8.140000
    },
    {
      "Date": 20130604, 
      "Value" : 11.680000
    },
    {
      "Date": 20130628, 
      "Value" : 8.620000
    },
    {
      "Date": 20131017, 
      "Value" : 11.670000
    },
    {
      "Date": 20131129, 
      "Value" : 11.360000
    },
    {
      "Date": 20140108, 
      "Value" : 9.630000
    },
    {
      "Date": 20140224, 
      "Value" : 19.580000
    },
    {
      "Date": 20140402, 
      "Value" : 12.840000
    },
    {
      "Date": 20140428, 
      "Value" : 16.219999
    },
    {
      "Date": 20140521, 
      "Value" : 11.800000
    },
    {
      "Date": 20140703, 
      "Value" : 16.010000
    },
    {
      "Date": 20141127, 
      "Value" : 29.950001
    },
    {
      "Date": 20141223, 
      "Value" : 20.879999
    },
    {
      "Date": 20150121, 
      "Value" : 26.080000
    },
    {
      "Date": 20150212, 
      "Value" : 22.309999
    },
    {
      "Date": 20150521, 
      "Value" : 40.430000
    },
    {
      "Date": 20150902, 
      "Value" : 17.900000
    },
    {
      "Date": 20151112, 
      "Value" : 29.330000
    },
    {
      "Date": 20151224, 
      "Value" : 30.010000
    },
    {
      "Date": 20160127, 
      "Value" : 21.770000
    },
    {
      "Date": 20160419, 
      "Value" : 32.480000
    },
    {
      "Date": 20160718, 
      "Value" : 31.180000
    },
    {
      "Date": 20160815, 
      "Value" : 28.900000
    },
    {
      "Date": 20161118, 
      "Value" : 40.080002
    },
    {
      "Date": 20170119, 
      "Value" : 32.330002
    },
    {
      "Date": 20170320, 
      "Value" : 37.000000
    },
    {
      "Date": 20170830, 
      "Value" : 25.350000
    },
    {
      "Date": 20180214, 
      "Value" : 18.260000
    },
    {
      "Date": 20180510, 
      "Value" : 31.420000
    },
    {
      "Date": 20181019, 
      "Value" : 15.990000
    },
    {
      "Date": 20181116, 
      "Value" : 21.940001
    },
    {
      "Date": 20181220, 
      "Value" : 17.830000
    },
    {
      "Date": 20190402, 
      "Value" : 29.770000
    },
    {
      "Date": 20190703, 
      "Value" : 22.389999
    },
    {
      "Date": 20190812, 
      "Value" : 18.500000
    },
    {
      "Date": 20190827, 
      "Value" : 27.900000
    },
    {
      "Date": 20191203, 
      "Value" : 19.860001
    },
    {
      "Date": 20200804, 
      "Value" : 181.220001
    },
    {
      "Date": 20200916, 
      "Value" : 72.080002
    },
    {
      "Date": 20201019, 
      "Value" : 93.150002
    },
    {
      "Date": 20210325, 
      "Value" : 43.549999
    },
    {
      "Date": 20210519, 
      "Value" : 72.110001
    },
    {
      "Date": 20211108, 
      "Value" : 44.169998
    },
    {
      "Date": 20211129, 
      "Value" : 53.520000
    },
    {
      "Date": 20211221, 
      "Value" : 46.529999
    },
    {
      "Date": 20220104, 
      "Value" : 56.259998
    },
    {
      "Date": 20220426, 
      "Value" : 29.549999
    },
    {
      "Date": 20220926, 
      "Value" : 31.200001
    }
  ]
}