{
  "Color": "rgb(244, 55, 244)", 
  "Point": [
    {
      "Date": 20060510, 
      "Value" : 0.670000
    },
    {
      "Date": 20061019, 
      "Value" : 1.580000
    },
    {
      "Date": 20061114, 
      "Value" : 1.010000
    },
    {
      "Date": 20061214, 
      "Value" : 1.470000
    },
    {
      "Date": 20070105, 
      "Value" : 1.000000
    },
    {
      "Date": 20080708, 
      "Value" : 6.430000
    },
    {
      "Date": 20081107, 
      "Value" : 1.890000
    },
    {
      "Date": 20090720, 
      "Value" : 10.360000
    },
    {
      "Date": 20090901, 
      "Value" : 6.470000
    },
    {
      "Date": 20091207, 
      "Value" : 10.920000
    },
    {
      "Date": 20100201, 
      "Value" : 7.340000
    },
    {
      "Date": 20100324, 
      "Value" : 9.550000
    },
    {
      "Date": 20100702, 
      "Value" : 5.570000
    },
    {
      "Date": 20110406, 
      "Value" : 11.860000
    },
    {
      "Date": 20110620, 
      "Value" : 7.010000
    },
    {
      "Date": 20110817, 
      "Value" : 9.740000
    },
    {
      "Date": 20110919, 
      "Value" : 7.340000
    },
    {
      "Date": 20111108, 
      "Value" : 9.600000
    },
    {
      "Date": 20111228, 
      "Value" : 4.800000
    },
    {
      "Date": 20120222, 
      "Value" : 7.010000
    },
    {
      "Date": 20120321, 
      "Value" : 6.040000
    },
    {
      "Date": 20120524, 
      "Value" : 12.010000
    },
    {
      "Date": 20120731, 
      "Value" : 8.210000
    },
    {
      "Date": 20121114, 
      "Value" : 11.050000
    },
    {
      "Date": 20121204, 
      "Value" : 7.660000
    },
    {
      "Date": 20130520, 
      "Value" : 14.440000
    },
    {
      "Date": 20130709, 
      "Value" : 7.810000
    },
    {
      "Date": 20130805, 
      "Value" : 11.960000
    },
    {
      "Date": 20130917, 
      "Value" : 9.940000
    },
    {
      "Date": 20131230, 
      "Value" : 17.250000
    },
    {
      "Date": 20140619, 
      "Value" : 9.490000
    },
    {
      "Date": 20141016, 
      "Value" : 14.830000
    },
    {
      "Date": 20141114, 
      "Value" : 12.770000
    },
    {
      "Date": 20150615, 
      "Value" : 58.459999
    },
    {
      "Date": 20160526, 
      "Value" : 19.559999
    },
    {
      "Date": 20160719, 
      "Value" : 28.740000
    },
    {
      "Date": 20160928, 
      "Value" : 19.459999
    },
    {
      "Date": 20161220, 
      "Value" : 24.040001
    },
    {
      "Date": 20170119, 
      "Value" : 17.360001
    },
    {
      "Date": 20170413, 
      "Value" : 22.660000
    },
    {
      "Date": 20170614, 
      "Value" : 17.260000
    },
    {
      "Date": 20171204, 
      "Value" : 35.599998
    },
    {
      "Date": 20180206, 
      "Value" : 21.120001
    },
    {
      "Date": 20181203, 
      "Value" : 32.910000
    },
    {
      "Date": 20190123, 
      "Value" : 17.190001
    },
    {
      "Date": 20190410, 
      "Value" : 38.779999
    },
    {
      "Date": 20190520, 
      "Value" : 27.860001
    },
    {
      "Date": 20191218, 
      "Value" : 109.480003
    },
    {
      "Date": 20200108, 
      "Value" : 89.830002
    },
    {
      "Date": 20200226, 
      "Value" : 171.360001
    },
    {
      "Date": 20200427, 
      "Value" : 89.660004
    },
    {
      "Date": 20200713, 
      "Value" : 167.380005
    },
    {
      "Date": 20201228, 
      "Value" : 92.330002
    },
    {
      "Date": 20210122, 
      "Value" : 131.000000
    },
    {
      "Date": 20210510, 
      "Value" : 77.500000
    },
    {
      "Date": 20210708, 
      "Value" : 104.790001
    },
    {
      "Date": 20210726, 
      "Value" : 85.400002
    },
    {
      "Date": 20210831, 
      "Value" : 124.760002
    },
    {
      "Date": 20210930, 
      "Value" : 92.470001
    },
    {
      "Date": 20211215, 
      "Value" : 143.679993
    },
    {
      "Date": 20220214, 
      "Value" : 105.449997
    },
    {
      "Date": 20220303, 
      "Value" : 120.660004
    },
    {
      "Date": 20220510, 
      "Value" : 58.150002
    },
    {
      "Date": 20220630, 
      "Value" : 86.320000
    },
    {
      "Date": 20221028, 
      "Value" : 43.450001
    },
    {
      "Date": 20221117, 
      "Value" : 62.029999
    },
    {
      "Date": 20230103, 
      "Value" : 51.680000
    },
    {
      "Date": 20230214, 
      "Value" : 61.500000
    },
    {
      "Date": 20230316, 
      "Value" : 49.200001
    },
    {
      "Date": 20230418, 
      "Value" : 66.330002
    },
    {
      "Date": 20230525, 
      "Value" : 51.110001
    }
  ]
}