{
  "Color": "rgb(244, 55, 244)", 
  "Point": [
    {
      "Date": 20060525, 
      "Value" : 1.850000
    },
    {
      "Date": 20061010, 
      "Value" : 3.290000
    },
    {
      "Date": 20061117, 
      "Value" : 2.110000
    },
    {
      "Date": 20070427, 
      "Value" : 6.290000
    },
    {
      "Date": 20070706, 
      "Value" : 3.190000
    },
    {
      "Date": 20070803, 
      "Value" : 5.550000
    },
    {
      "Date": 20071025, 
      "Value" : 3.250000
    },
    {
      "Date": 20080121, 
      "Value" : 6.070000
    },
    {
      "Date": 20080201, 
      "Value" : 4.040000
    },
    {
      "Date": 20080307, 
      "Value" : 5.600000
    },
    {
      "Date": 20080423, 
      "Value" : 2.400000
    },
    {
      "Date": 20080605, 
      "Value" : 3.730000
    },
    {
      "Date": 20080703, 
      "Value" : 2.190000
    },
    {
      "Date": 20080728, 
      "Value" : 2.850000
    },
    {
      "Date": 20081104, 
      "Value" : 0.970000
    },
    {
      "Date": 20090507, 
      "Value" : 7.000000
    },
    {
      "Date": 20090525, 
      "Value" : 5.710000
    },
    {
      "Date": 20091111, 
      "Value" : 15.490000
    },
    {
      "Date": 20091223, 
      "Value" : 12.410000
    },
    {
      "Date": 20100115, 
      "Value" : 16.020000
    },
    {
      "Date": 20100203, 
      "Value" : 12.140000
    },
    {
      "Date": 20100413, 
      "Value" : 24.209999
    },
    {
      "Date": 20100505, 
      "Value" : 15.970000
    },
    {
      "Date": 20100611, 
      "Value" : 24.600000
    },
    {
      "Date": 20100702, 
      "Value" : 17.440001
    },
    {
      "Date": 20100920, 
      "Value" : 28.969999
    },
    {
      "Date": 20110127, 
      "Value" : 14.190000
    },
    {
      "Date": 20110324, 
      "Value" : 19.910000
    },
    {
      "Date": 20110621, 
      "Value" : 12.470000
    },
    {
      "Date": 20110711, 
      "Value" : 17.240000
    },
    {
      "Date": 20111024, 
      "Value" : 10.870000
    },
    {
      "Date": 20111117, 
      "Value" : 13.110000
    },
    {
      "Date": 20120106, 
      "Value" : 6.140000
    },
    {
      "Date": 20120309, 
      "Value" : 10.160000
    },
    {
      "Date": 20120711, 
      "Value" : 6.580000
    },
    {
      "Date": 20121025, 
      "Value" : 9.590000
    },
    {
      "Date": 20121204, 
      "Value" : 6.990000
    },
    {
      "Date": 20130604, 
      "Value" : 18.010000
    },
    {
      "Date": 20131111, 
      "Value" : 11.520000
    },
    {
      "Date": 20131129, 
      "Value" : 17.469999
    },
    {
      "Date": 20131223, 
      "Value" : 13.640000
    },
    {
      "Date": 20140217, 
      "Value" : 17.780001
    },
    {
      "Date": 20140523, 
      "Value" : 12.270000
    },
    {
      "Date": 20141215, 
      "Value" : 40.400002
    },
    {
      "Date": 20150112, 
      "Value" : 29.700001
    },
    {
      "Date": 20150325, 
      "Value" : 42.720001
    },
    {
      "Date": 20150420, 
      "Value" : 35.540001
    },
    {
      "Date": 20150601, 
      "Value" : 83.769997
    },
    {
      "Date": 20150827, 
      "Value" : 26.709999
    },
    {
      "Date": 20160419, 
      "Value" : 49.459999
    },
    {
      "Date": 20160512, 
      "Value" : 38.540001
    },
    {
      "Date": 20160711, 
      "Value" : 54.270000
    },
    {
      "Date": 20160929, 
      "Value" : 40.680000
    },
    {
      "Date": 20161122, 
      "Value" : 45.099998
    },
    {
      "Date": 20161220, 
      "Value" : 40.139999
    },
    {
      "Date": 20170209, 
      "Value" : 47.180000
    },
    {
      "Date": 20170602, 
      "Value" : 32.970001
    },
    {
      "Date": 20170622, 
      "Value" : 38.340000
    },
    {
      "Date": 20170721, 
      "Value" : 33.020000
    },
    {
      "Date": 20170824, 
      "Value" : 34.439999
    },
    {
      "Date": 20170915, 
      "Value" : 32.660000
    },
    {
      "Date": 20171115, 
      "Value" : 42.730000
    },
    {
      "Date": 20180207, 
      "Value" : 23.930000
    },
    {
      "Date": 20180426, 
      "Value" : 37.810001
    },
    {
      "Date": 20180809, 
      "Value" : 19.000000
    },
    {
      "Date": 20180925, 
      "Value" : 26.250000
    },
    {
      "Date": 20181030, 
      "Value" : 18.209999
    },
    {
      "Date": 20181122, 
      "Value" : 22.620001
    },
    {
      "Date": 20190102, 
      "Value" : 19.209999
    },
    {
      "Date": 20190404, 
      "Value" : 35.820000
    },
    {
      "Date": 20190620, 
      "Value" : 24.650000
    },
    {
      "Date": 20190910, 
      "Value" : 36.520000
    },
    {
      "Date": 20200204, 
      "Value" : 21.230000
    },
    {
      "Date": 20200226, 
      "Value" : 29.360001
    },
    {
      "Date": 20200528, 
      "Value" : 21.180000
    },
    {
      "Date": 20200810, 
      "Value" : 32.880001
    },
    {
      "Date": 20201117, 
      "Value" : 21.900000
    },
    {
      "Date": 20210106, 
      "Value" : 30.180000
    },
    {
      "Date": 20210208, 
      "Value" : 23.110001
    },
    {
      "Date": 20210319, 
      "Value" : 28.820000
    },
    {
      "Date": 20210728, 
      "Value" : 20.139999
    },
    {
      "Date": 20210830, 
      "Value" : 24.280001
    },
    {
      "Date": 20210917, 
      "Value" : 21.459999
    },
    {
      "Date": 20211207, 
      "Value" : 37.400002
    },
    {
      "Date": 20220427, 
      "Value" : 18.889999
    },
    {
      "Date": 20220606, 
      "Value" : 26.330000
    },
    {
      "Date": 20220712, 
      "Value" : 22.570000
    },
    {
      "Date": 20220810, 
      "Value" : 25.990000
    },
    {
      "Date": 20221012, 
      "Value" : 19.370001
    },
    {
      "Date": 20221206, 
      "Value" : 26.719999
    },
    {
      "Date": 20230111, 
      "Value" : 21.969999
    },
    {
      "Date": 20230327, 
      "Value" : 27.240000
    },
    {
      "Date": 20230517, 
      "Value" : 22.570000
    },
    {
      "Date": 20230704, 
      "Value" : 24.610001
    },
    {
      "Date": 20231023, 
      "Value" : 19.799999
    },
    {
      "Date": 20231120, 
      "Value" : 22.580000
    },
    {
      "Date": 20240208, 
      "Value" : 11.000000
    },
    {
      "Date": 20240322, 
      "Value" : 20.670000
    },
    {
      "Date": 20240416, 
      "Value" : 13.840000
    },
    {
      "Date": 20240510, 
      "Value" : 27.290001
    },
    {
      "Date": 20240829, 
      "Value" : 14.270000
    },
    {
      "Date": 20241031, 
      "Value" : 30.850000
    },
    {
      "Date": 20250113, 
      "Value" : 18.709999
    },
    {
      "Date": 20250213, 
      "Value" : 24.799999
    },
    {
      "Date": 20250409, 
      "Value" : 16.700001
    },
    {
      "Date": 20250512, 
      "Value" : 24.580000
    }
  ]
}