{
  "Color": "rgb(244, 55, 244)", 
  "Point": [
    {
      "Date": 20170509, 
      "Value" : 3.190000
    },
    {
      "Date": 20170601, 
      "Value" : 7.730000
    },
    {
      "Date": 20170811, 
      "Value" : 4.650000
    },
    {
      "Date": 20171013, 
      "Value" : 6.180000
    },
    {
      "Date": 20171208, 
      "Value" : 4.590000
    },
    {
      "Date": 20180112, 
      "Value" : 6.000000
    },
    {
      "Date": 20180209, 
      "Value" : 4.210000
    },
    {
      "Date": 20180411, 
      "Value" : 7.220000
    },
    {
      "Date": 20180622, 
      "Value" : 4.200000
    },
    {
      "Date": 20180713, 
      "Value" : 5.570000
    },
    {
      "Date": 20181019, 
      "Value" : 2.880000
    },
    {
      "Date": 20181122, 
      "Value" : 3.830000
    },
    {
      "Date": 20190131, 
      "Value" : 3.000000
    },
    {
      "Date": 20190408, 
      "Value" : 4.640000
    },
    {
      "Date": 20190610, 
      "Value" : 3.500000
    },
    {
      "Date": 20190712, 
      "Value" : 4.020000
    },
    {
      "Date": 20190809, 
      "Value" : 3.480000
    },
    {
      "Date": 20200214, 
      "Value" : 8.990000
    },
    {
      "Date": 20200317, 
      "Value" : 6.100000
    },
    {
      "Date": 20200714, 
      "Value" : 24.610001
    },
    {
      "Date": 20200812, 
      "Value" : 17.270000
    },
    {
      "Date": 20200824, 
      "Value" : 20.750000
    },
    {
      "Date": 20201201, 
      "Value" : 13.950000
    },
    {
      "Date": 20201215, 
      "Value" : 17.350000
    },
    {
      "Date": 20210930, 
      "Value" : 12.100000
    },
    {
      "Date": 20211201, 
      "Value" : 22.200001
    },
    {
      "Date": 20220110, 
      "Value" : 16.540001
    },
    {
      "Date": 20220513, 
      "Value" : 43.680000
    },
    {
      "Date": 20220614, 
      "Value" : 21.420000
    },
    {
      "Date": 20220715, 
      "Value" : 40.389999
    },
    {
      "Date": 20221011, 
      "Value" : 15.890000
    },
    {
      "Date": 20221111, 
      "Value" : 22.059999
    },
    {
      "Date": 20230824, 
      "Value" : 12.590000
    },
    {
      "Date": 20231013, 
      "Value" : 17.430000
    },
    {
      "Date": 20231221, 
      "Value" : 13.020000
    }
  ]
}