{
  "Color": "rgb(244, 55, 244)", 
  "Point": [
    {
      "Date": 20210225, 
      "Value" : 31.650000
    },
    {
      "Date": 20220427, 
      "Value" : 13.160000
    },
    {
      "Date": 20220824, 
      "Value" : 37.950001
    },
    {
      "Date": 20221010, 
      "Value" : 24.840000
    },
    {
      "Date": 20221109, 
      "Value" : 31.740000
    },
    {
      "Date": 20221223, 
      "Value" : 24.379999
    },
    {
      "Date": 20230209, 
      "Value" : 44.430000
    },
    {
      "Date": 20230510, 
      "Value" : 25.889999
    },
    {
      "Date": 20230712, 
      "Value" : 39.189999
    },
    {
      "Date": 20230821, 
      "Value" : 29.559999
    },
    {
      "Date": 20230920, 
      "Value" : 33.099998
    }
  ]
}