{
  "Color": "rgb(244, 55, 244)", 
  "Point": [
    {
      "Date": 20210316, 
      "Value" : 76.000000
    },
    {
      "Date": 20210602, 
      "Value" : 106.190002
    },
    {
      "Date": 20211103, 
      "Value" : 47.509998
    },
    {
      "Date": 20211201, 
      "Value" : 60.790001
    },
    {
      "Date": 20220110, 
      "Value" : 48.230000
    },
    {
      "Date": 20220121, 
      "Value" : 70.800003
    },
    {
      "Date": 20220427, 
      "Value" : 28.000000
    },
    {
      "Date": 20220608, 
      "Value" : 39.880001
    },
    {
      "Date": 20220927, 
      "Value" : 26.500000
    },
    {
      "Date": 20220930, 
      "Value" : 26.450001
    }
  ]
}