{
  "Color": "rgb(244, 55, 244)", 
  "Point": [
    {
      "Date": 20230712, 
      "Value" : 9.740000
    },
    {
      "Date": 20231023, 
      "Value" : 6.950000
    },
    {
      "Date": 20240104, 
      "Value" : 19.530001
    },
    {
      "Date": 20240208, 
      "Value" : 11.220000
    },
    {
      "Date": 20240228, 
      "Value" : 23.830000
    },
    {
      "Date": 20240416, 
      "Value" : 12.350000
    },
    {
      "Date": 20240507, 
      "Value" : 18.709999
    },
    {
      "Date": 20240606, 
      "Value" : 15.820000
    },
    {
      "Date": 20240718, 
      "Value" : 23.799999
    },
    {
      "Date": 20240812, 
      "Value" : 17.010000
    },
    {
      "Date": 20241115, 
      "Value" : 61.750000
    },
    {
      "Date": 20250108, 
      "Value" : 35.509998
    },
    {
      "Date": 20250305, 
      "Value" : 58.990002
    },
    {
      "Date": 20250409, 
      "Value" : 36.240002
    },
    {
      "Date": 20250425, 
      "Value" : 57.490002
    }
  ]
}