{
  "Color": "rgb(244, 55, 244)", 
  "Point": [
    {
      "Date": 20161223, 
      "Value" : 4.230000
    },
    {
      "Date": 20170328, 
      "Value" : 21.270000
    },
    {
      "Date": 20181019, 
      "Value" : 8.130000
    },
    {
      "Date": 20200825, 
      "Value" : 45.230000
    },
    {
      "Date": 20221011, 
      "Value" : 18.770000
    },
    {
      "Date": 20230419, 
      "Value" : 39.930000
    },
    {
      "Date": 20240206, 
      "Value" : 15.870000
    },
    {
      "Date": 20241202, 
      "Value" : 36.910000
    },
    {
      "Date": 20250409, 
      "Value" : 23.500000
    }
  ]
}