{
  "Color": "rgb(244, 55, 244)", 
  "Point": [
    {
      "Date": 20200619, 
      "Value" : 24.089418
    },
    {
      "Date": 20200622, 
      "Value" : 24.089418
    },
    {
      "Date": 20200623, 
      "Value" : 24.089418
    },
    {
      "Date": 20200624, 
      "Value" : 24.089418
    },
    {
      "Date": 20200629, 
      "Value" : 24.089418
    },
    {
      "Date": 20200630, 
      "Value" : 24.089418
    },
    {
      "Date": 20200701, 
      "Value" : 24.089418
    },
    {
      "Date": 20200702, 
      "Value" : 24.089418
    },
    {
      "Date": 20200703, 
      "Value" : 24.089418
    },
    {
      "Date": 20200706, 
      "Value" : 24.089418
    },
    {
      "Date": 20200707, 
      "Value" : 24.089418
    },
    {
      "Date": 20200708, 
      "Value" : 24.089418
    },
    {
      "Date": 20200709, 
      "Value" : 24.089418
    },
    {
      "Date": 20200710, 
      "Value" : 24.089418
    },
    {
      "Date": 20200713, 
      "Value" : 24.089418
    },
    {
      "Date": 20200714, 
      "Value" : 24.089418
    },
    {
      "Date": 20200715, 
      "Value" : 24.089418
    },
    {
      "Date": 20200716, 
      "Value" : 24.089418
    },
    {
      "Date": 20200717, 
      "Value" : 24.089418
    },
    {
      "Date": 20200720, 
      "Value" : 24.089418
    },
    {
      "Date": 20200721, 
      "Value" : 24.089418
    },
    {
      "Date": 20200722, 
      "Value" : 24.089418
    },
    {
      "Date": 20200723, 
      "Value" : 24.089418
    },
    {
      "Date": 20200724, 
      "Value" : 24.089418
    },
    {
      "Date": 20200727, 
      "Value" : 24.089418
    },
    {
      "Date": 20200728, 
      "Value" : 24.089418
    },
    {
      "Date": 20200729, 
      "Value" : 24.089418
    },
    {
      "Date": 20200730, 
      "Value" : 24.089418
    },
    {
      "Date": 20200731, 
      "Value" : 24.089418
    },
    {
      "Date": 20200803, 
      "Value" : 24.089418
    },
    {
      "Date": 20200804, 
      "Value" : 24.089418
    },
    {
      "Date": 20200805, 
      "Value" : 24.089418
    },
    {
      "Date": 20200806, 
      "Value" : 24.089418
    },
    {
      "Date": 20200807, 
      "Value" : 24.089418
    },
    {
      "Date": 20200810, 
      "Value" : 24.089418
    },
    {
      "Date": 20200811, 
      "Value" : 24.089418
    },
    {
      "Date": 20200812, 
      "Value" : 24.089418
    },
    {
      "Date": 20200813, 
      "Value" : 24.089418
    },
    {
      "Date": 20200814, 
      "Value" : 24.089418
    },
    {
      "Date": 20200817, 
      "Value" : 24.089418
    },
    {
      "Date": 20200818, 
      "Value" : 24.089418
    },
    {
      "Date": 20200819, 
      "Value" : 24.089418
    },
    {
      "Date": 20200820, 
      "Value" : 24.089418
    },
    {
      "Date": 20200821, 
      "Value" : 24.089418
    },
    {
      "Date": 20200824, 
      "Value" : 24.089418
    },
    {
      "Date": 20200825, 
      "Value" : 24.089418
    },
    {
      "Date": 20200826, 
      "Value" : 24.089418
    },
    {
      "Date": 20200827, 
      "Value" : 24.089418
    },
    {
      "Date": 20200828, 
      "Value" : 24.089418
    },
    {
      "Date": 20200831, 
      "Value" : 24.089418
    },
    {
      "Date": 20200901, 
      "Value" : 24.089418
    },
    {
      "Date": 20200902, 
      "Value" : 24.089418
    },
    {
      "Date": 20200903, 
      "Value" : 24.089418
    },
    {
      "Date": 20200904, 
      "Value" : 24.089418
    },
    {
      "Date": 20200907, 
      "Value" : 24.089418
    },
    {
      "Date": 20200908, 
      "Value" : 24.089418
    },
    {
      "Date": 20200909, 
      "Value" : 24.089418
    },
    {
      "Date": 20200910, 
      "Value" : 24.089418
    },
    {
      "Date": 20200911, 
      "Value" : 24.089418
    },
    {
      "Date": 20200914, 
      "Value" : 24.089418
    },
    {
      "Date": 20200915, 
      "Value" : 24.089418
    },
    {
      "Date": 20200916, 
      "Value" : 24.089418
    },
    {
      "Date": 20200917, 
      "Value" : 24.089418
    },
    {
      "Date": 20200918, 
      "Value" : 24.089418
    },
    {
      "Date": 20200921, 
      "Value" : 24.089418
    },
    {
      "Date": 20200922, 
      "Value" : 24.089418
    },
    {
      "Date": 20200923, 
      "Value" : 24.089418
    },
    {
      "Date": 20200924, 
      "Value" : 24.089418
    },
    {
      "Date": 20200925, 
      "Value" : 24.089418
    },
    {
      "Date": 20200928, 
      "Value" : 24.089418
    },
    {
      "Date": 20200929, 
      "Value" : 24.089418
    },
    {
      "Date": 20200930, 
      "Value" : 24.089418
    },
    {
      "Date": 20201009, 
      "Value" : 24.089418
    },
    {
      "Date": 20201012, 
      "Value" : 24.089418
    },
    {
      "Date": 20201013, 
      "Value" : 24.089418
    },
    {
      "Date": 20201014, 
      "Value" : 24.089418
    },
    {
      "Date": 20201015, 
      "Value" : 24.089418
    },
    {
      "Date": 20201016, 
      "Value" : 24.089418
    },
    {
      "Date": 20201019, 
      "Value" : 24.089418
    },
    {
      "Date": 20201020, 
      "Value" : 24.089418
    },
    {
      "Date": 20201021, 
      "Value" : 24.089418
    },
    {
      "Date": 20201022, 
      "Value" : 24.089418
    },
    {
      "Date": 20201023, 
      "Value" : 24.089418
    },
    {
      "Date": 20201026, 
      "Value" : 24.089418
    },
    {
      "Date": 20201027, 
      "Value" : 24.089418
    },
    {
      "Date": 20201028, 
      "Value" : 24.089418
    },
    {
      "Date": 20201029, 
      "Value" : 24.089418
    },
    {
      "Date": 20201030, 
      "Value" : 24.089418
    },
    {
      "Date": 20201102, 
      "Value" : 24.089418
    },
    {
      "Date": 20201103, 
      "Value" : 24.089418
    },
    {
      "Date": 20201104, 
      "Value" : 24.089418
    },
    {
      "Date": 20201104, 
      "Value" : 24.015005
    },
    {
      "Date": 20201104, 
      "Value" : 24.015005
    },
    {
      "Date": 20201103, 
      "Value" : 24.015005
    },
    {
      "Date": 20201102, 
      "Value" : 24.015005
    },
    {
      "Date": 20201030, 
      "Value" : 24.015005
    },
    {
      "Date": 20201029, 
      "Value" : 24.015005
    },
    {
      "Date": 20201028, 
      "Value" : 24.015005
    },
    {
      "Date": 20201027, 
      "Value" : 24.015005
    },
    {
      "Date": 20201026, 
      "Value" : 24.015005
    },
    {
      "Date": 20201023, 
      "Value" : 24.015005
    },
    {
      "Date": 20201022, 
      "Value" : 24.015005
    },
    {
      "Date": 20201021, 
      "Value" : 24.015005
    },
    {
      "Date": 20201020, 
      "Value" : 24.015005
    },
    {
      "Date": 20201019, 
      "Value" : 24.015005
    },
    {
      "Date": 20201016, 
      "Value" : 24.015005
    },
    {
      "Date": 20201015, 
      "Value" : 24.015005
    },
    {
      "Date": 20201014, 
      "Value" : 24.015005
    },
    {
      "Date": 20201013, 
      "Value" : 24.015005
    },
    {
      "Date": 20201012, 
      "Value" : 24.015005
    },
    {
      "Date": 20201009, 
      "Value" : 24.015005
    },
    {
      "Date": 20200930, 
      "Value" : 24.015005
    },
    {
      "Date": 20200929, 
      "Value" : 24.015005
    },
    {
      "Date": 20200928, 
      "Value" : 24.015005
    },
    {
      "Date": 20200925, 
      "Value" : 24.015005
    },
    {
      "Date": 20200924, 
      "Value" : 24.015005
    },
    {
      "Date": 20200923, 
      "Value" : 24.015005
    },
    {
      "Date": 20200922, 
      "Value" : 24.015005
    },
    {
      "Date": 20200921, 
      "Value" : 24.015005
    },
    {
      "Date": 20200918, 
      "Value" : 24.015005
    },
    {
      "Date": 20200917, 
      "Value" : 24.015005
    },
    {
      "Date": 20200916, 
      "Value" : 24.015005
    },
    {
      "Date": 20200915, 
      "Value" : 24.015005
    },
    {
      "Date": 20200914, 
      "Value" : 24.015005
    },
    {
      "Date": 20200911, 
      "Value" : 24.015005
    },
    {
      "Date": 20200910, 
      "Value" : 24.015005
    },
    {
      "Date": 20200909, 
      "Value" : 24.015005
    },
    {
      "Date": 20200908, 
      "Value" : 24.015005
    },
    {
      "Date": 20200907, 
      "Value" : 24.015005
    },
    {
      "Date": 20200904, 
      "Value" : 24.015005
    },
    {
      "Date": 20200903, 
      "Value" : 24.015005
    },
    {
      "Date": 20200902, 
      "Value" : 24.015005
    },
    {
      "Date": 20200901, 
      "Value" : 24.015005
    },
    {
      "Date": 20200831, 
      "Value" : 24.015005
    },
    {
      "Date": 20200828, 
      "Value" : 24.015005
    },
    {
      "Date": 20200827, 
      "Value" : 24.015005
    },
    {
      "Date": 20200826, 
      "Value" : 24.015005
    },
    {
      "Date": 20200825, 
      "Value" : 24.015005
    },
    {
      "Date": 20200824, 
      "Value" : 24.015005
    },
    {
      "Date": 20200821, 
      "Value" : 24.015005
    },
    {
      "Date": 20200820, 
      "Value" : 24.015005
    },
    {
      "Date": 20200819, 
      "Value" : 24.015005
    },
    {
      "Date": 20200818, 
      "Value" : 24.015005
    },
    {
      "Date": 20200817, 
      "Value" : 24.015005
    },
    {
      "Date": 20200814, 
      "Value" : 24.015005
    },
    {
      "Date": 20200813, 
      "Value" : 24.015005
    },
    {
      "Date": 20200812, 
      "Value" : 24.015005
    },
    {
      "Date": 20200811, 
      "Value" : 24.015005
    },
    {
      "Date": 20200810, 
      "Value" : 24.015005
    },
    {
      "Date": 20200807, 
      "Value" : 24.015005
    },
    {
      "Date": 20200806, 
      "Value" : 24.015005
    },
    {
      "Date": 20200805, 
      "Value" : 24.015005
    },
    {
      "Date": 20200804, 
      "Value" : 24.015005
    },
    {
      "Date": 20200803, 
      "Value" : 24.015005
    },
    {
      "Date": 20200731, 
      "Value" : 24.015005
    },
    {
      "Date": 20200730, 
      "Value" : 24.015005
    },
    {
      "Date": 20200729, 
      "Value" : 24.015005
    },
    {
      "Date": 20200728, 
      "Value" : 24.015005
    },
    {
      "Date": 20200727, 
      "Value" : 24.015005
    },
    {
      "Date": 20200724, 
      "Value" : 24.015005
    },
    {
      "Date": 20200723, 
      "Value" : 24.015005
    },
    {
      "Date": 20200722, 
      "Value" : 24.015005
    },
    {
      "Date": 20200721, 
      "Value" : 24.015005
    },
    {
      "Date": 20200720, 
      "Value" : 24.015005
    },
    {
      "Date": 20200717, 
      "Value" : 24.015005
    },
    {
      "Date": 20200716, 
      "Value" : 24.015005
    },
    {
      "Date": 20200715, 
      "Value" : 24.015005
    },
    {
      "Date": 20200714, 
      "Value" : 24.015005
    },
    {
      "Date": 20200713, 
      "Value" : 24.015005
    },
    {
      "Date": 20200710, 
      "Value" : 24.015005
    },
    {
      "Date": 20200709, 
      "Value" : 24.015005
    },
    {
      "Date": 20200708, 
      "Value" : 24.015005
    },
    {
      "Date": 20200707, 
      "Value" : 24.015005
    },
    {
      "Date": 20200706, 
      "Value" : 24.015005
    },
    {
      "Date": 20200703, 
      "Value" : 24.015005
    },
    {
      "Date": 20200702, 
      "Value" : 24.015005
    },
    {
      "Date": 20200701, 
      "Value" : 24.015005
    },
    {
      "Date": 20200630, 
      "Value" : 24.015005
    },
    {
      "Date": 20200629, 
      "Value" : 24.015005
    },
    {
      "Date": 20200624, 
      "Value" : 24.015005
    },
    {
      "Date": 20200623, 
      "Value" : 24.015005
    },
    {
      "Date": 20200622, 
      "Value" : 24.015005
    },
    {
      "Date": 20200619, 
      "Value" : 24.015005
    },
    {
      "Date": 20200619, 
      "Value" : 24.089418
    },
    {
      "Date": 20200619, 
      "Value" : -1.000000
    },
    {
      "Date": 20221102, 
      "Value" : 61.557350
    },
    {
      "Date": 20221103, 
      "Value" : 61.557350
    },
    {
      "Date": 20221104, 
      "Value" : 61.557350
    },
    {
      "Date": 20221107, 
      "Value" : 61.557350
    },
    {
      "Date": 20221108, 
      "Value" : 61.557350
    },
    {
      "Date": 20221109, 
      "Value" : 61.557350
    },
    {
      "Date": 20221110, 
      "Value" : 61.557350
    },
    {
      "Date": 20221111, 
      "Value" : 61.557350
    },
    {
      "Date": 20221114, 
      "Value" : 61.557350
    },
    {
      "Date": 20221115, 
      "Value" : 61.557350
    },
    {
      "Date": 20221116, 
      "Value" : 61.557350
    },
    {
      "Date": 20221117, 
      "Value" : 61.557350
    },
    {
      "Date": 20221118, 
      "Value" : 61.557350
    },
    {
      "Date": 20221121, 
      "Value" : 61.557350
    },
    {
      "Date": 20221122, 
      "Value" : 61.557350
    },
    {
      "Date": 20221123, 
      "Value" : 61.557350
    },
    {
      "Date": 20221124, 
      "Value" : 61.557350
    },
    {
      "Date": 20221125, 
      "Value" : 61.557350
    },
    {
      "Date": 20221128, 
      "Value" : 61.557350
    },
    {
      "Date": 20221129, 
      "Value" : 61.557350
    },
    {
      "Date": 20221130, 
      "Value" : 61.557350
    },
    {
      "Date": 20221201, 
      "Value" : 61.557350
    },
    {
      "Date": 20221202, 
      "Value" : 61.557350
    },
    {
      "Date": 20221205, 
      "Value" : 61.557350
    },
    {
      "Date": 20221206, 
      "Value" : 61.557350
    },
    {
      "Date": 20221207, 
      "Value" : 61.557350
    },
    {
      "Date": 20221208, 
      "Value" : 61.557350
    },
    {
      "Date": 20221209, 
      "Value" : 61.557350
    },
    {
      "Date": 20221212, 
      "Value" : 61.557350
    },
    {
      "Date": 20221213, 
      "Value" : 61.557350
    },
    {
      "Date": 20221214, 
      "Value" : 61.557350
    },
    {
      "Date": 20221215, 
      "Value" : 61.557350
    },
    {
      "Date": 20221216, 
      "Value" : 61.557350
    },
    {
      "Date": 20221219, 
      "Value" : 61.557350
    },
    {
      "Date": 20221220, 
      "Value" : 61.557350
    },
    {
      "Date": 20221221, 
      "Value" : 61.557350
    },
    {
      "Date": 20221222, 
      "Value" : 61.557350
    },
    {
      "Date": 20221223, 
      "Value" : 61.557350
    },
    {
      "Date": 20221226, 
      "Value" : 61.557350
    },
    {
      "Date": 20221227, 
      "Value" : 61.557350
    },
    {
      "Date": 20221228, 
      "Value" : 61.557350
    },
    {
      "Date": 20221229, 
      "Value" : 61.557350
    },
    {
      "Date": 20221230, 
      "Value" : 61.557350
    },
    {
      "Date": 20230103, 
      "Value" : 61.557350
    },
    {
      "Date": 20230104, 
      "Value" : 61.557350
    },
    {
      "Date": 20230105, 
      "Value" : 61.557350
    },
    {
      "Date": 20230106, 
      "Value" : 61.557350
    },
    {
      "Date": 20230109, 
      "Value" : 61.557350
    },
    {
      "Date": 20230110, 
      "Value" : 61.557350
    },
    {
      "Date": 20230111, 
      "Value" : 61.557350
    },
    {
      "Date": 20230112, 
      "Value" : 61.557350
    },
    {
      "Date": 20230113, 
      "Value" : 61.557350
    },
    {
      "Date": 20230116, 
      "Value" : 61.557350
    },
    {
      "Date": 20230117, 
      "Value" : 61.557350
    },
    {
      "Date": 20230118, 
      "Value" : 61.557350
    },
    {
      "Date": 20230119, 
      "Value" : 61.557350
    },
    {
      "Date": 20230120, 
      "Value" : 61.557350
    },
    {
      "Date": 20230130, 
      "Value" : 61.557350
    },
    {
      "Date": 20230131, 
      "Value" : 61.557350
    },
    {
      "Date": 20230201, 
      "Value" : 61.557350
    },
    {
      "Date": 20230202, 
      "Value" : 61.557350
    },
    {
      "Date": 20230203, 
      "Value" : 61.557350
    },
    {
      "Date": 20230206, 
      "Value" : 61.557350
    },
    {
      "Date": 20230207, 
      "Value" : 61.557350
    },
    {
      "Date": 20230208, 
      "Value" : 61.557350
    },
    {
      "Date": 20230209, 
      "Value" : 61.557350
    },
    {
      "Date": 20230210, 
      "Value" : 61.557350
    },
    {
      "Date": 20230213, 
      "Value" : 61.557350
    },
    {
      "Date": 20230214, 
      "Value" : 61.557350
    },
    {
      "Date": 20230215, 
      "Value" : 61.557350
    },
    {
      "Date": 20230216, 
      "Value" : 61.557350
    },
    {
      "Date": 20230217, 
      "Value" : 61.557350
    },
    {
      "Date": 20230220, 
      "Value" : 61.557350
    },
    {
      "Date": 20230221, 
      "Value" : 61.557350
    },
    {
      "Date": 20230222, 
      "Value" : 61.557350
    },
    {
      "Date": 20230223, 
      "Value" : 61.557350
    },
    {
      "Date": 20230224, 
      "Value" : 61.557350
    },
    {
      "Date": 20230227, 
      "Value" : 61.557350
    },
    {
      "Date": 20230228, 
      "Value" : 61.557350
    },
    {
      "Date": 20230301, 
      "Value" : 61.557350
    },
    {
      "Date": 20230302, 
      "Value" : 61.557350
    },
    {
      "Date": 20230303, 
      "Value" : 61.557350
    },
    {
      "Date": 20230306, 
      "Value" : 61.557350
    },
    {
      "Date": 20230307, 
      "Value" : 61.557350
    },
    {
      "Date": 20230308, 
      "Value" : 61.557350
    },
    {
      "Date": 20230309, 
      "Value" : 61.557350
    },
    {
      "Date": 20230310, 
      "Value" : 61.557350
    },
    {
      "Date": 20230313, 
      "Value" : 61.557350
    },
    {
      "Date": 20230314, 
      "Value" : 61.557350
    },
    {
      "Date": 20230315, 
      "Value" : 61.557350
    },
    {
      "Date": 20230316, 
      "Value" : 61.557350
    },
    {
      "Date": 20230317, 
      "Value" : 61.557350
    },
    {
      "Date": 20230320, 
      "Value" : 61.557350
    },
    {
      "Date": 20230321, 
      "Value" : 61.557350
    },
    {
      "Date": 20230322, 
      "Value" : 61.557350
    },
    {
      "Date": 20230323, 
      "Value" : 61.557350
    },
    {
      "Date": 20230324, 
      "Value" : 61.557350
    },
    {
      "Date": 20230327, 
      "Value" : 61.557350
    },
    {
      "Date": 20230328, 
      "Value" : 61.557350
    },
    {
      "Date": 20230329, 
      "Value" : 61.557350
    },
    {
      "Date": 20230330, 
      "Value" : 61.557350
    },
    {
      "Date": 20230331, 
      "Value" : 61.557350
    },
    {
      "Date": 20230403, 
      "Value" : 61.557350
    },
    {
      "Date": 20230404, 
      "Value" : 61.557350
    },
    {
      "Date": 20230404, 
      "Value" : 59.758541
    },
    {
      "Date": 20230404, 
      "Value" : 59.758541
    },
    {
      "Date": 20230403, 
      "Value" : 59.758541
    },
    {
      "Date": 20230331, 
      "Value" : 59.758541
    },
    {
      "Date": 20230330, 
      "Value" : 59.758541
    },
    {
      "Date": 20230329, 
      "Value" : 59.758541
    },
    {
      "Date": 20230328, 
      "Value" : 59.758541
    },
    {
      "Date": 20230327, 
      "Value" : 59.758541
    },
    {
      "Date": 20230324, 
      "Value" : 59.758541
    },
    {
      "Date": 20230323, 
      "Value" : 59.758541
    },
    {
      "Date": 20230322, 
      "Value" : 59.758541
    },
    {
      "Date": 20230321, 
      "Value" : 59.758541
    },
    {
      "Date": 20230320, 
      "Value" : 59.758541
    },
    {
      "Date": 20230317, 
      "Value" : 59.758541
    },
    {
      "Date": 20230316, 
      "Value" : 59.758541
    },
    {
      "Date": 20230315, 
      "Value" : 59.758541
    },
    {
      "Date": 20230314, 
      "Value" : 59.758541
    },
    {
      "Date": 20230313, 
      "Value" : 59.758541
    },
    {
      "Date": 20230310, 
      "Value" : 59.758541
    },
    {
      "Date": 20230309, 
      "Value" : 59.758541
    },
    {
      "Date": 20230308, 
      "Value" : 59.758541
    },
    {
      "Date": 20230307, 
      "Value" : 59.758541
    },
    {
      "Date": 20230306, 
      "Value" : 59.758541
    },
    {
      "Date": 20230303, 
      "Value" : 59.758541
    },
    {
      "Date": 20230302, 
      "Value" : 59.758541
    },
    {
      "Date": 20230301, 
      "Value" : 59.758541
    },
    {
      "Date": 20230228, 
      "Value" : 59.758541
    },
    {
      "Date": 20230227, 
      "Value" : 59.758541
    },
    {
      "Date": 20230224, 
      "Value" : 59.758541
    },
    {
      "Date": 20230223, 
      "Value" : 59.758541
    },
    {
      "Date": 20230222, 
      "Value" : 59.758541
    },
    {
      "Date": 20230221, 
      "Value" : 59.758541
    },
    {
      "Date": 20230220, 
      "Value" : 59.758541
    },
    {
      "Date": 20230217, 
      "Value" : 59.758541
    },
    {
      "Date": 20230216, 
      "Value" : 59.758541
    },
    {
      "Date": 20230215, 
      "Value" : 59.758541
    },
    {
      "Date": 20230214, 
      "Value" : 59.758541
    },
    {
      "Date": 20230213, 
      "Value" : 59.758541
    },
    {
      "Date": 20230210, 
      "Value" : 59.758541
    },
    {
      "Date": 20230209, 
      "Value" : 59.758541
    },
    {
      "Date": 20230208, 
      "Value" : 59.758541
    },
    {
      "Date": 20230207, 
      "Value" : 59.758541
    },
    {
      "Date": 20230206, 
      "Value" : 59.758541
    },
    {
      "Date": 20230203, 
      "Value" : 59.758541
    },
    {
      "Date": 20230202, 
      "Value" : 59.758541
    },
    {
      "Date": 20230201, 
      "Value" : 59.758541
    },
    {
      "Date": 20230131, 
      "Value" : 59.758541
    },
    {
      "Date": 20230130, 
      "Value" : 59.758541
    },
    {
      "Date": 20230120, 
      "Value" : 59.758541
    },
    {
      "Date": 20230119, 
      "Value" : 59.758541
    },
    {
      "Date": 20230118, 
      "Value" : 59.758541
    },
    {
      "Date": 20230117, 
      "Value" : 59.758541
    },
    {
      "Date": 20230116, 
      "Value" : 59.758541
    },
    {
      "Date": 20230113, 
      "Value" : 59.758541
    },
    {
      "Date": 20230112, 
      "Value" : 59.758541
    },
    {
      "Date": 20230111, 
      "Value" : 59.758541
    },
    {
      "Date": 20230110, 
      "Value" : 59.758541
    },
    {
      "Date": 20230109, 
      "Value" : 59.758541
    },
    {
      "Date": 20230106, 
      "Value" : 59.758541
    },
    {
      "Date": 20230105, 
      "Value" : 59.758541
    },
    {
      "Date": 20230104, 
      "Value" : 59.758541
    },
    {
      "Date": 20230103, 
      "Value" : 59.758541
    },
    {
      "Date": 20221230, 
      "Value" : 59.758541
    },
    {
      "Date": 20221229, 
      "Value" : 59.758541
    },
    {
      "Date": 20221228, 
      "Value" : 59.758541
    },
    {
      "Date": 20221227, 
      "Value" : 59.758541
    },
    {
      "Date": 20221226, 
      "Value" : 59.758541
    },
    {
      "Date": 20221223, 
      "Value" : 59.758541
    },
    {
      "Date": 20221222, 
      "Value" : 59.758541
    },
    {
      "Date": 20221221, 
      "Value" : 59.758541
    },
    {
      "Date": 20221220, 
      "Value" : 59.758541
    },
    {
      "Date": 20221219, 
      "Value" : 59.758541
    },
    {
      "Date": 20221216, 
      "Value" : 59.758541
    },
    {
      "Date": 20221215, 
      "Value" : 59.758541
    },
    {
      "Date": 20221214, 
      "Value" : 59.758541
    },
    {
      "Date": 20221213, 
      "Value" : 59.758541
    },
    {
      "Date": 20221212, 
      "Value" : 59.758541
    },
    {
      "Date": 20221209, 
      "Value" : 59.758541
    },
    {
      "Date": 20221208, 
      "Value" : 59.758541
    },
    {
      "Date": 20221207, 
      "Value" : 59.758541
    },
    {
      "Date": 20221206, 
      "Value" : 59.758541
    },
    {
      "Date": 20221205, 
      "Value" : 59.758541
    },
    {
      "Date": 20221202, 
      "Value" : 59.758541
    },
    {
      "Date": 20221201, 
      "Value" : 59.758541
    },
    {
      "Date": 20221130, 
      "Value" : 59.758541
    },
    {
      "Date": 20221129, 
      "Value" : 59.758541
    },
    {
      "Date": 20221128, 
      "Value" : 59.758541
    },
    {
      "Date": 20221125, 
      "Value" : 59.758541
    },
    {
      "Date": 20221124, 
      "Value" : 59.758541
    },
    {
      "Date": 20221123, 
      "Value" : 59.758541
    },
    {
      "Date": 20221122, 
      "Value" : 59.758541
    },
    {
      "Date": 20221121, 
      "Value" : 59.758541
    },
    {
      "Date": 20221118, 
      "Value" : 59.758541
    },
    {
      "Date": 20221117, 
      "Value" : 59.758541
    },
    {
      "Date": 20221116, 
      "Value" : 59.758541
    },
    {
      "Date": 20221115, 
      "Value" : 59.758541
    },
    {
      "Date": 20221114, 
      "Value" : 59.758541
    },
    {
      "Date": 20221111, 
      "Value" : 59.758541
    },
    {
      "Date": 20221110, 
      "Value" : 59.758541
    },
    {
      "Date": 20221109, 
      "Value" : 59.758541
    },
    {
      "Date": 20221108, 
      "Value" : 59.758541
    },
    {
      "Date": 20221107, 
      "Value" : 59.758541
    },
    {
      "Date": 20221104, 
      "Value" : 59.758541
    },
    {
      "Date": 20221103, 
      "Value" : 59.758541
    },
    {
      "Date": 20221102, 
      "Value" : 59.758541
    },
    {
      "Date": 20221102, 
      "Value" : 61.557350
    },
    {
      "Date": 20221102, 
      "Value" : 0.000000
    },
    {
      "Date": 20231027, 
      "Value" : 56.419708
    },
    {
      "Date": 20231030, 
      "Value" : 56.419708
    },
    {
      "Date": 20231031, 
      "Value" : 56.419708
    },
    {
      "Date": 20231101, 
      "Value" : 56.419708
    },
    {
      "Date": 20231102, 
      "Value" : 56.419708
    },
    {
      "Date": 20231103, 
      "Value" : 56.419708
    },
    {
      "Date": 20231106, 
      "Value" : 56.419708
    },
    {
      "Date": 20231107, 
      "Value" : 56.419708
    },
    {
      "Date": 20231108, 
      "Value" : 56.419708
    },
    {
      "Date": 20231109, 
      "Value" : 56.419708
    },
    {
      "Date": 20231110, 
      "Value" : 56.419708
    },
    {
      "Date": 20231113, 
      "Value" : 56.419708
    },
    {
      "Date": 20231114, 
      "Value" : 56.419708
    },
    {
      "Date": 20231115, 
      "Value" : 56.419708
    },
    {
      "Date": 20231116, 
      "Value" : 56.419708
    },
    {
      "Date": 20231117, 
      "Value" : 56.419708
    },
    {
      "Date": 20231120, 
      "Value" : 56.419708
    },
    {
      "Date": 20231121, 
      "Value" : 56.419708
    },
    {
      "Date": 20231122, 
      "Value" : 56.419708
    },
    {
      "Date": 20231123, 
      "Value" : 56.419708
    },
    {
      "Date": 20231124, 
      "Value" : 56.419708
    },
    {
      "Date": 20231127, 
      "Value" : 56.419708
    },
    {
      "Date": 20231128, 
      "Value" : 56.419708
    },
    {
      "Date": 20231129, 
      "Value" : 56.419708
    },
    {
      "Date": 20231130, 
      "Value" : 56.419708
    },
    {
      "Date": 20231201, 
      "Value" : 56.419708
    },
    {
      "Date": 20231204, 
      "Value" : 56.419708
    },
    {
      "Date": 20231205, 
      "Value" : 56.419708
    },
    {
      "Date": 20231206, 
      "Value" : 56.419708
    },
    {
      "Date": 20231207, 
      "Value" : 56.419708
    },
    {
      "Date": 20231208, 
      "Value" : 56.419708
    },
    {
      "Date": 20231211, 
      "Value" : 56.419708
    },
    {
      "Date": 20231212, 
      "Value" : 56.419708
    },
    {
      "Date": 20231213, 
      "Value" : 56.419708
    },
    {
      "Date": 20231214, 
      "Value" : 56.419708
    },
    {
      "Date": 20231215, 
      "Value" : 56.419708
    },
    {
      "Date": 20231218, 
      "Value" : 56.419708
    },
    {
      "Date": 20231219, 
      "Value" : 56.419708
    },
    {
      "Date": 20231220, 
      "Value" : 56.419708
    },
    {
      "Date": 20231221, 
      "Value" : 56.419708
    },
    {
      "Date": 20231222, 
      "Value" : 56.419708
    },
    {
      "Date": 20231225, 
      "Value" : 56.419708
    },
    {
      "Date": 20231226, 
      "Value" : 56.419708
    },
    {
      "Date": 20231227, 
      "Value" : 56.419708
    },
    {
      "Date": 20231228, 
      "Value" : 56.419708
    },
    {
      "Date": 20231229, 
      "Value" : 56.419708
    },
    {
      "Date": 20240102, 
      "Value" : 56.419708
    },
    {
      "Date": 20240103, 
      "Value" : 56.419708
    },
    {
      "Date": 20240104, 
      "Value" : 56.419708
    },
    {
      "Date": 20240105, 
      "Value" : 56.419708
    },
    {
      "Date": 20240108, 
      "Value" : 56.419708
    },
    {
      "Date": 20240109, 
      "Value" : 56.419708
    },
    {
      "Date": 20240110, 
      "Value" : 56.419708
    },
    {
      "Date": 20240111, 
      "Value" : 56.419708
    },
    {
      "Date": 20240112, 
      "Value" : 56.419708
    },
    {
      "Date": 20240115, 
      "Value" : 56.419708
    },
    {
      "Date": 20240116, 
      "Value" : 56.419708
    },
    {
      "Date": 20240117, 
      "Value" : 56.419708
    },
    {
      "Date": 20240118, 
      "Value" : 56.419708
    },
    {
      "Date": 20240119, 
      "Value" : 56.419708
    },
    {
      "Date": 20240122, 
      "Value" : 56.419708
    },
    {
      "Date": 20240123, 
      "Value" : 56.419708
    },
    {
      "Date": 20240124, 
      "Value" : 56.419708
    },
    {
      "Date": 20240125, 
      "Value" : 56.419708
    },
    {
      "Date": 20240126, 
      "Value" : 56.419708
    },
    {
      "Date": 20240129, 
      "Value" : 56.419708
    },
    {
      "Date": 20240130, 
      "Value" : 56.419708
    },
    {
      "Date": 20240131, 
      "Value" : 56.419708
    },
    {
      "Date": 20240201, 
      "Value" : 56.419708
    },
    {
      "Date": 20240202, 
      "Value" : 56.419708
    },
    {
      "Date": 20240205, 
      "Value" : 56.419708
    },
    {
      "Date": 20240206, 
      "Value" : 56.419708
    },
    {
      "Date": 20240207, 
      "Value" : 56.419708
    },
    {
      "Date": 20240208, 
      "Value" : 56.419708
    },
    {
      "Date": 20240219, 
      "Value" : 56.419708
    },
    {
      "Date": 20240220, 
      "Value" : 56.419708
    },
    {
      "Date": 20240221, 
      "Value" : 56.419708
    },
    {
      "Date": 20240222, 
      "Value" : 56.419708
    },
    {
      "Date": 20240223, 
      "Value" : 56.419708
    },
    {
      "Date": 20240226, 
      "Value" : 56.419708
    },
    {
      "Date": 20240227, 
      "Value" : 56.419708
    },
    {
      "Date": 20240228, 
      "Value" : 56.419708
    },
    {
      "Date": 20240229, 
      "Value" : 56.419708
    },
    {
      "Date": 20240301, 
      "Value" : 56.419708
    },
    {
      "Date": 20240304, 
      "Value" : 56.419708
    },
    {
      "Date": 20240305, 
      "Value" : 56.419708
    },
    {
      "Date": 20240306, 
      "Value" : 56.419708
    },
    {
      "Date": 20240307, 
      "Value" : 56.419708
    },
    {
      "Date": 20240308, 
      "Value" : 56.419708
    },
    {
      "Date": 20240311, 
      "Value" : 56.419708
    },
    {
      "Date": 20240312, 
      "Value" : 56.419708
    },
    {
      "Date": 20240313, 
      "Value" : 56.419708
    },
    {
      "Date": 20240314, 
      "Value" : 56.419708
    },
    {
      "Date": 20240315, 
      "Value" : 56.419708
    },
    {
      "Date": 20240318, 
      "Value" : 56.419708
    },
    {
      "Date": 20240319, 
      "Value" : 56.419708
    },
    {
      "Date": 20240320, 
      "Value" : 56.419708
    },
    {
      "Date": 20240321, 
      "Value" : 56.419708
    },
    {
      "Date": 20240322, 
      "Value" : 56.419708
    },
    {
      "Date": 20240322, 
      "Value" : 52.798225
    },
    {
      "Date": 20240322, 
      "Value" : 52.798225
    },
    {
      "Date": 20240321, 
      "Value" : 52.798225
    },
    {
      "Date": 20240320, 
      "Value" : 52.798225
    },
    {
      "Date": 20240319, 
      "Value" : 52.798225
    },
    {
      "Date": 20240318, 
      "Value" : 52.798225
    },
    {
      "Date": 20240315, 
      "Value" : 52.798225
    },
    {
      "Date": 20240314, 
      "Value" : 52.798225
    },
    {
      "Date": 20240313, 
      "Value" : 52.798225
    },
    {
      "Date": 20240312, 
      "Value" : 52.798225
    },
    {
      "Date": 20240311, 
      "Value" : 52.798225
    },
    {
      "Date": 20240308, 
      "Value" : 52.798225
    },
    {
      "Date": 20240307, 
      "Value" : 52.798225
    },
    {
      "Date": 20240306, 
      "Value" : 52.798225
    },
    {
      "Date": 20240305, 
      "Value" : 52.798225
    },
    {
      "Date": 20240304, 
      "Value" : 52.798225
    },
    {
      "Date": 20240301, 
      "Value" : 52.798225
    },
    {
      "Date": 20240229, 
      "Value" : 52.798225
    },
    {
      "Date": 20240228, 
      "Value" : 52.798225
    },
    {
      "Date": 20240227, 
      "Value" : 52.798225
    },
    {
      "Date": 20240226, 
      "Value" : 52.798225
    },
    {
      "Date": 20240223, 
      "Value" : 52.798225
    },
    {
      "Date": 20240222, 
      "Value" : 52.798225
    },
    {
      "Date": 20240221, 
      "Value" : 52.798225
    },
    {
      "Date": 20240220, 
      "Value" : 52.798225
    },
    {
      "Date": 20240219, 
      "Value" : 52.798225
    },
    {
      "Date": 20240208, 
      "Value" : 52.798225
    },
    {
      "Date": 20240207, 
      "Value" : 52.798225
    },
    {
      "Date": 20240206, 
      "Value" : 52.798225
    },
    {
      "Date": 20240205, 
      "Value" : 52.798225
    },
    {
      "Date": 20240202, 
      "Value" : 52.798225
    },
    {
      "Date": 20240201, 
      "Value" : 52.798225
    },
    {
      "Date": 20240131, 
      "Value" : 52.798225
    },
    {
      "Date": 20240130, 
      "Value" : 52.798225
    },
    {
      "Date": 20240129, 
      "Value" : 52.798225
    },
    {
      "Date": 20240126, 
      "Value" : 52.798225
    },
    {
      "Date": 20240125, 
      "Value" : 52.798225
    },
    {
      "Date": 20240124, 
      "Value" : 52.798225
    },
    {
      "Date": 20240123, 
      "Value" : 52.798225
    },
    {
      "Date": 20240122, 
      "Value" : 52.798225
    },
    {
      "Date": 20240119, 
      "Value" : 52.798225
    },
    {
      "Date": 20240118, 
      "Value" : 52.798225
    },
    {
      "Date": 20240117, 
      "Value" : 52.798225
    },
    {
      "Date": 20240116, 
      "Value" : 52.798225
    },
    {
      "Date": 20240115, 
      "Value" : 52.798225
    },
    {
      "Date": 20240112, 
      "Value" : 52.798225
    },
    {
      "Date": 20240111, 
      "Value" : 52.798225
    },
    {
      "Date": 20240110, 
      "Value" : 52.798225
    },
    {
      "Date": 20240109, 
      "Value" : 52.798225
    },
    {
      "Date": 20240108, 
      "Value" : 52.798225
    },
    {
      "Date": 20240105, 
      "Value" : 52.798225
    },
    {
      "Date": 20240104, 
      "Value" : 52.798225
    },
    {
      "Date": 20240103, 
      "Value" : 52.798225
    },
    {
      "Date": 20240102, 
      "Value" : 52.798225
    },
    {
      "Date": 20231229, 
      "Value" : 52.798225
    },
    {
      "Date": 20231228, 
      "Value" : 52.798225
    },
    {
      "Date": 20231227, 
      "Value" : 52.798225
    },
    {
      "Date": 20231226, 
      "Value" : 52.798225
    },
    {
      "Date": 20231225, 
      "Value" : 52.798225
    },
    {
      "Date": 20231222, 
      "Value" : 52.798225
    },
    {
      "Date": 20231221, 
      "Value" : 52.798225
    },
    {
      "Date": 20231220, 
      "Value" : 52.798225
    },
    {
      "Date": 20231219, 
      "Value" : 52.798225
    },
    {
      "Date": 20231218, 
      "Value" : 52.798225
    },
    {
      "Date": 20231215, 
      "Value" : 52.798225
    },
    {
      "Date": 20231214, 
      "Value" : 52.798225
    },
    {
      "Date": 20231213, 
      "Value" : 52.798225
    },
    {
      "Date": 20231212, 
      "Value" : 52.798225
    },
    {
      "Date": 20231211, 
      "Value" : 52.798225
    },
    {
      "Date": 20231208, 
      "Value" : 52.798225
    },
    {
      "Date": 20231207, 
      "Value" : 52.798225
    },
    {
      "Date": 20231206, 
      "Value" : 52.798225
    },
    {
      "Date": 20231205, 
      "Value" : 52.798225
    },
    {
      "Date": 20231204, 
      "Value" : 52.798225
    },
    {
      "Date": 20231201, 
      "Value" : 52.798225
    },
    {
      "Date": 20231130, 
      "Value" : 52.798225
    },
    {
      "Date": 20231129, 
      "Value" : 52.798225
    },
    {
      "Date": 20231128, 
      "Value" : 52.798225
    },
    {
      "Date": 20231127, 
      "Value" : 52.798225
    },
    {
      "Date": 20231124, 
      "Value" : 52.798225
    },
    {
      "Date": 20231123, 
      "Value" : 52.798225
    },
    {
      "Date": 20231122, 
      "Value" : 52.798225
    },
    {
      "Date": 20231121, 
      "Value" : 52.798225
    },
    {
      "Date": 20231120, 
      "Value" : 52.798225
    },
    {
      "Date": 20231117, 
      "Value" : 52.798225
    },
    {
      "Date": 20231116, 
      "Value" : 52.798225
    },
    {
      "Date": 20231115, 
      "Value" : 52.798225
    },
    {
      "Date": 20231114, 
      "Value" : 52.798225
    },
    {
      "Date": 20231113, 
      "Value" : 52.798225
    },
    {
      "Date": 20231110, 
      "Value" : 52.798225
    },
    {
      "Date": 20231109, 
      "Value" : 52.798225
    },
    {
      "Date": 20231108, 
      "Value" : 52.798225
    },
    {
      "Date": 20231107, 
      "Value" : 52.798225
    },
    {
      "Date": 20231106, 
      "Value" : 52.798225
    },
    {
      "Date": 20231103, 
      "Value" : 52.798225
    },
    {
      "Date": 20231102, 
      "Value" : 52.798225
    },
    {
      "Date": 20231101, 
      "Value" : 52.798225
    },
    {
      "Date": 20231031, 
      "Value" : 52.798225
    },
    {
      "Date": 20231030, 
      "Value" : 52.798225
    },
    {
      "Date": 20231027, 
      "Value" : 52.798225
    },
    {
      "Date": 20231027, 
      "Value" : 56.419708
    },
    {
      "Date": 20231027, 
      "Value" : -1.000000
    }
  ]
}