{
  "Color": "rgb(244, 55, 244)", 
  "Point": [
    {
      "Date": 20170607, 
      "Value" : 39.699715
    },
    {
      "Date": 20170608, 
      "Value" : 39.699715
    },
    {
      "Date": 20170609, 
      "Value" : 39.699715
    },
    {
      "Date": 20170612, 
      "Value" : 39.699715
    },
    {
      "Date": 20170613, 
      "Value" : 39.699715
    },
    {
      "Date": 20170614, 
      "Value" : 39.699715
    },
    {
      "Date": 20170615, 
      "Value" : 39.699715
    },
    {
      "Date": 20170616, 
      "Value" : 39.699715
    },
    {
      "Date": 20170619, 
      "Value" : 39.699715
    },
    {
      "Date": 20170620, 
      "Value" : 39.699715
    },
    {
      "Date": 20170621, 
      "Value" : 39.699715
    },
    {
      "Date": 20170622, 
      "Value" : 39.699715
    },
    {
      "Date": 20170623, 
      "Value" : 39.699715
    },
    {
      "Date": 20170626, 
      "Value" : 39.699715
    },
    {
      "Date": 20170627, 
      "Value" : 39.699715
    },
    {
      "Date": 20170628, 
      "Value" : 39.699715
    },
    {
      "Date": 20170629, 
      "Value" : 39.699715
    },
    {
      "Date": 20170630, 
      "Value" : 39.699715
    },
    {
      "Date": 20170703, 
      "Value" : 39.699715
    },
    {
      "Date": 20170704, 
      "Value" : 39.699715
    },
    {
      "Date": 20170705, 
      "Value" : 39.699715
    },
    {
      "Date": 20170706, 
      "Value" : 39.699715
    },
    {
      "Date": 20170707, 
      "Value" : 39.699715
    },
    {
      "Date": 20170710, 
      "Value" : 39.699715
    },
    {
      "Date": 20170711, 
      "Value" : 39.699715
    },
    {
      "Date": 20170712, 
      "Value" : 39.699715
    },
    {
      "Date": 20170713, 
      "Value" : 39.699715
    },
    {
      "Date": 20170714, 
      "Value" : 39.699715
    },
    {
      "Date": 20170717, 
      "Value" : 39.699715
    },
    {
      "Date": 20170718, 
      "Value" : 39.699715
    },
    {
      "Date": 20170719, 
      "Value" : 39.699715
    },
    {
      "Date": 20170720, 
      "Value" : 39.699715
    },
    {
      "Date": 20170721, 
      "Value" : 39.699715
    },
    {
      "Date": 20170724, 
      "Value" : 39.699715
    },
    {
      "Date": 20170725, 
      "Value" : 39.699715
    },
    {
      "Date": 20170726, 
      "Value" : 39.699715
    },
    {
      "Date": 20170727, 
      "Value" : 39.699715
    },
    {
      "Date": 20170728, 
      "Value" : 39.699715
    },
    {
      "Date": 20170731, 
      "Value" : 39.699715
    },
    {
      "Date": 20170801, 
      "Value" : 39.699715
    },
    {
      "Date": 20170802, 
      "Value" : 39.699715
    },
    {
      "Date": 20170803, 
      "Value" : 39.699715
    },
    {
      "Date": 20170804, 
      "Value" : 39.699715
    },
    {
      "Date": 20170807, 
      "Value" : 39.699715
    },
    {
      "Date": 20170808, 
      "Value" : 39.699715
    },
    {
      "Date": 20170809, 
      "Value" : 39.699715
    },
    {
      "Date": 20170810, 
      "Value" : 39.699715
    },
    {
      "Date": 20170811, 
      "Value" : 39.699715
    },
    {
      "Date": 20170814, 
      "Value" : 39.699715
    },
    {
      "Date": 20170815, 
      "Value" : 39.699715
    },
    {
      "Date": 20170816, 
      "Value" : 39.699715
    },
    {
      "Date": 20170817, 
      "Value" : 39.699715
    },
    {
      "Date": 20170818, 
      "Value" : 39.699715
    },
    {
      "Date": 20170821, 
      "Value" : 39.699715
    },
    {
      "Date": 20170822, 
      "Value" : 39.699715
    },
    {
      "Date": 20170823, 
      "Value" : 39.699715
    },
    {
      "Date": 20170824, 
      "Value" : 39.699715
    },
    {
      "Date": 20170825, 
      "Value" : 39.699715
    },
    {
      "Date": 20170828, 
      "Value" : 39.699715
    },
    {
      "Date": 20170829, 
      "Value" : 39.699715
    },
    {
      "Date": 20170830, 
      "Value" : 39.699715
    },
    {
      "Date": 20170831, 
      "Value" : 39.699715
    },
    {
      "Date": 20170901, 
      "Value" : 39.699715
    },
    {
      "Date": 20170904, 
      "Value" : 39.699715
    },
    {
      "Date": 20170905, 
      "Value" : 39.699715
    },
    {
      "Date": 20170906, 
      "Value" : 39.699715
    },
    {
      "Date": 20170907, 
      "Value" : 39.699715
    },
    {
      "Date": 20170908, 
      "Value" : 39.699715
    },
    {
      "Date": 20170911, 
      "Value" : 39.699715
    },
    {
      "Date": 20170912, 
      "Value" : 39.699715
    },
    {
      "Date": 20170913, 
      "Value" : 39.699715
    },
    {
      "Date": 20170914, 
      "Value" : 39.699715
    },
    {
      "Date": 20170915, 
      "Value" : 39.699715
    },
    {
      "Date": 20170918, 
      "Value" : 39.699715
    },
    {
      "Date": 20170919, 
      "Value" : 39.699715
    },
    {
      "Date": 20170920, 
      "Value" : 39.699715
    },
    {
      "Date": 20170921, 
      "Value" : 39.699715
    },
    {
      "Date": 20170922, 
      "Value" : 39.699715
    },
    {
      "Date": 20170925, 
      "Value" : 39.699715
    },
    {
      "Date": 20170926, 
      "Value" : 39.699715
    },
    {
      "Date": 20170927, 
      "Value" : 39.699715
    },
    {
      "Date": 20170928, 
      "Value" : 39.699715
    },
    {
      "Date": 20170928, 
      "Value" : 36.142929
    },
    {
      "Date": 20170928, 
      "Value" : 36.142929
    },
    {
      "Date": 20170927, 
      "Value" : 36.142929
    },
    {
      "Date": 20170926, 
      "Value" : 36.142929
    },
    {
      "Date": 20170925, 
      "Value" : 36.142929
    },
    {
      "Date": 20170922, 
      "Value" : 36.142929
    },
    {
      "Date": 20170921, 
      "Value" : 36.142929
    },
    {
      "Date": 20170920, 
      "Value" : 36.142929
    },
    {
      "Date": 20170919, 
      "Value" : 36.142929
    },
    {
      "Date": 20170918, 
      "Value" : 36.142929
    },
    {
      "Date": 20170915, 
      "Value" : 36.142929
    },
    {
      "Date": 20170914, 
      "Value" : 36.142929
    },
    {
      "Date": 20170913, 
      "Value" : 36.142929
    },
    {
      "Date": 20170912, 
      "Value" : 36.142929
    },
    {
      "Date": 20170911, 
      "Value" : 36.142929
    },
    {
      "Date": 20170908, 
      "Value" : 36.142929
    },
    {
      "Date": 20170907, 
      "Value" : 36.142929
    },
    {
      "Date": 20170906, 
      "Value" : 36.142929
    },
    {
      "Date": 20170905, 
      "Value" : 36.142929
    },
    {
      "Date": 20170904, 
      "Value" : 36.142929
    },
    {
      "Date": 20170901, 
      "Value" : 36.142929
    },
    {
      "Date": 20170831, 
      "Value" : 36.142929
    },
    {
      "Date": 20170830, 
      "Value" : 36.142929
    },
    {
      "Date": 20170829, 
      "Value" : 36.142929
    },
    {
      "Date": 20170828, 
      "Value" : 36.142929
    },
    {
      "Date": 20170825, 
      "Value" : 36.142929
    },
    {
      "Date": 20170824, 
      "Value" : 36.142929
    },
    {
      "Date": 20170823, 
      "Value" : 36.142929
    },
    {
      "Date": 20170822, 
      "Value" : 36.142929
    },
    {
      "Date": 20170821, 
      "Value" : 36.142929
    },
    {
      "Date": 20170818, 
      "Value" : 36.142929
    },
    {
      "Date": 20170817, 
      "Value" : 36.142929
    },
    {
      "Date": 20170816, 
      "Value" : 36.142929
    },
    {
      "Date": 20170815, 
      "Value" : 36.142929
    },
    {
      "Date": 20170814, 
      "Value" : 36.142929
    },
    {
      "Date": 20170811, 
      "Value" : 36.142929
    },
    {
      "Date": 20170810, 
      "Value" : 36.142929
    },
    {
      "Date": 20170809, 
      "Value" : 36.142929
    },
    {
      "Date": 20170808, 
      "Value" : 36.142929
    },
    {
      "Date": 20170807, 
      "Value" : 36.142929
    },
    {
      "Date": 20170804, 
      "Value" : 36.142929
    },
    {
      "Date": 20170803, 
      "Value" : 36.142929
    },
    {
      "Date": 20170802, 
      "Value" : 36.142929
    },
    {
      "Date": 20170801, 
      "Value" : 36.142929
    },
    {
      "Date": 20170731, 
      "Value" : 36.142929
    },
    {
      "Date": 20170728, 
      "Value" : 36.142929
    },
    {
      "Date": 20170727, 
      "Value" : 36.142929
    },
    {
      "Date": 20170726, 
      "Value" : 36.142929
    },
    {
      "Date": 20170725, 
      "Value" : 36.142929
    },
    {
      "Date": 20170724, 
      "Value" : 36.142929
    },
    {
      "Date": 20170721, 
      "Value" : 36.142929
    },
    {
      "Date": 20170720, 
      "Value" : 36.142929
    },
    {
      "Date": 20170719, 
      "Value" : 36.142929
    },
    {
      "Date": 20170718, 
      "Value" : 36.142929
    },
    {
      "Date": 20170717, 
      "Value" : 36.142929
    },
    {
      "Date": 20170714, 
      "Value" : 36.142929
    },
    {
      "Date": 20170713, 
      "Value" : 36.142929
    },
    {
      "Date": 20170712, 
      "Value" : 36.142929
    },
    {
      "Date": 20170711, 
      "Value" : 36.142929
    },
    {
      "Date": 20170710, 
      "Value" : 36.142929
    },
    {
      "Date": 20170707, 
      "Value" : 36.142929
    },
    {
      "Date": 20170706, 
      "Value" : 36.142929
    },
    {
      "Date": 20170705, 
      "Value" : 36.142929
    },
    {
      "Date": 20170704, 
      "Value" : 36.142929
    },
    {
      "Date": 20170703, 
      "Value" : 36.142929
    },
    {
      "Date": 20170630, 
      "Value" : 36.142929
    },
    {
      "Date": 20170629, 
      "Value" : 36.142929
    },
    {
      "Date": 20170628, 
      "Value" : 36.142929
    },
    {
      "Date": 20170627, 
      "Value" : 36.142929
    },
    {
      "Date": 20170626, 
      "Value" : 36.142929
    },
    {
      "Date": 20170623, 
      "Value" : 36.142929
    },
    {
      "Date": 20170622, 
      "Value" : 36.142929
    },
    {
      "Date": 20170621, 
      "Value" : 36.142929
    },
    {
      "Date": 20170620, 
      "Value" : 36.142929
    },
    {
      "Date": 20170619, 
      "Value" : 36.142929
    },
    {
      "Date": 20170616, 
      "Value" : 36.142929
    },
    {
      "Date": 20170615, 
      "Value" : 36.142929
    },
    {
      "Date": 20170614, 
      "Value" : 36.142929
    },
    {
      "Date": 20170613, 
      "Value" : 36.142929
    },
    {
      "Date": 20170612, 
      "Value" : 36.142929
    },
    {
      "Date": 20170609, 
      "Value" : 36.142929
    },
    {
      "Date": 20170608, 
      "Value" : 36.142929
    },
    {
      "Date": 20170607, 
      "Value" : 36.142929
    },
    {
      "Date": 20170607, 
      "Value" : 39.699715
    },
    {
      "Date": 20170607, 
      "Value" : -1.000000
    },
    {
      "Date": 20200403, 
      "Value" : 51.003815
    },
    {
      "Date": 20200407, 
      "Value" : 51.003815
    },
    {
      "Date": 20200408, 
      "Value" : 51.003815
    },
    {
      "Date": 20200409, 
      "Value" : 51.003815
    },
    {
      "Date": 20200410, 
      "Value" : 51.003815
    },
    {
      "Date": 20200413, 
      "Value" : 51.003815
    },
    {
      "Date": 20200414, 
      "Value" : 51.003815
    },
    {
      "Date": 20200415, 
      "Value" : 51.003815
    },
    {
      "Date": 20200416, 
      "Value" : 51.003815
    },
    {
      "Date": 20200417, 
      "Value" : 51.003815
    },
    {
      "Date": 20200420, 
      "Value" : 51.003815
    },
    {
      "Date": 20200421, 
      "Value" : 51.003815
    },
    {
      "Date": 20200422, 
      "Value" : 51.003815
    },
    {
      "Date": 20200423, 
      "Value" : 51.003815
    },
    {
      "Date": 20200424, 
      "Value" : 51.003815
    },
    {
      "Date": 20200427, 
      "Value" : 51.003815
    },
    {
      "Date": 20200428, 
      "Value" : 51.003815
    },
    {
      "Date": 20200429, 
      "Value" : 51.003815
    },
    {
      "Date": 20200430, 
      "Value" : 51.003815
    },
    {
      "Date": 20200506, 
      "Value" : 51.003815
    },
    {
      "Date": 20200507, 
      "Value" : 51.003815
    },
    {
      "Date": 20200508, 
      "Value" : 51.003815
    },
    {
      "Date": 20200511, 
      "Value" : 51.003815
    },
    {
      "Date": 20200512, 
      "Value" : 51.003815
    },
    {
      "Date": 20200513, 
      "Value" : 51.003815
    },
    {
      "Date": 20200514, 
      "Value" : 51.003815
    },
    {
      "Date": 20200515, 
      "Value" : 51.003815
    },
    {
      "Date": 20200518, 
      "Value" : 51.003815
    },
    {
      "Date": 20200519, 
      "Value" : 51.003815
    },
    {
      "Date": 20200520, 
      "Value" : 51.003815
    },
    {
      "Date": 20200521, 
      "Value" : 51.003815
    },
    {
      "Date": 20200522, 
      "Value" : 51.003815
    },
    {
      "Date": 20200525, 
      "Value" : 51.003815
    },
    {
      "Date": 20200526, 
      "Value" : 51.003815
    },
    {
      "Date": 20200527, 
      "Value" : 51.003815
    },
    {
      "Date": 20200528, 
      "Value" : 51.003815
    },
    {
      "Date": 20200529, 
      "Value" : 51.003815
    },
    {
      "Date": 20200601, 
      "Value" : 51.003815
    },
    {
      "Date": 20200602, 
      "Value" : 51.003815
    },
    {
      "Date": 20200603, 
      "Value" : 51.003815
    },
    {
      "Date": 20200604, 
      "Value" : 51.003815
    },
    {
      "Date": 20200605, 
      "Value" : 51.003815
    },
    {
      "Date": 20200608, 
      "Value" : 51.003815
    },
    {
      "Date": 20200609, 
      "Value" : 51.003815
    },
    {
      "Date": 20200610, 
      "Value" : 51.003815
    },
    {
      "Date": 20200611, 
      "Value" : 51.003815
    },
    {
      "Date": 20200612, 
      "Value" : 51.003815
    },
    {
      "Date": 20200615, 
      "Value" : 51.003815
    },
    {
      "Date": 20200616, 
      "Value" : 51.003815
    },
    {
      "Date": 20200617, 
      "Value" : 51.003815
    },
    {
      "Date": 20200618, 
      "Value" : 51.003815
    },
    {
      "Date": 20200619, 
      "Value" : 51.003815
    },
    {
      "Date": 20200622, 
      "Value" : 51.003815
    },
    {
      "Date": 20200623, 
      "Value" : 51.003815
    },
    {
      "Date": 20200624, 
      "Value" : 51.003815
    },
    {
      "Date": 20200629, 
      "Value" : 51.003815
    },
    {
      "Date": 20200630, 
      "Value" : 51.003815
    },
    {
      "Date": 20200701, 
      "Value" : 51.003815
    },
    {
      "Date": 20200702, 
      "Value" : 51.003815
    },
    {
      "Date": 20200703, 
      "Value" : 51.003815
    },
    {
      "Date": 20200706, 
      "Value" : 51.003815
    },
    {
      "Date": 20200707, 
      "Value" : 51.003815
    },
    {
      "Date": 20200708, 
      "Value" : 51.003815
    },
    {
      "Date": 20200709, 
      "Value" : 51.003815
    },
    {
      "Date": 20200710, 
      "Value" : 51.003815
    },
    {
      "Date": 20200710, 
      "Value" : 48.763519
    },
    {
      "Date": 20200710, 
      "Value" : 48.763519
    },
    {
      "Date": 20200709, 
      "Value" : 48.763519
    },
    {
      "Date": 20200708, 
      "Value" : 48.763519
    },
    {
      "Date": 20200707, 
      "Value" : 48.763519
    },
    {
      "Date": 20200706, 
      "Value" : 48.763519
    },
    {
      "Date": 20200703, 
      "Value" : 48.763519
    },
    {
      "Date": 20200702, 
      "Value" : 48.763519
    },
    {
      "Date": 20200701, 
      "Value" : 48.763519
    },
    {
      "Date": 20200630, 
      "Value" : 48.763519
    },
    {
      "Date": 20200629, 
      "Value" : 48.763519
    },
    {
      "Date": 20200624, 
      "Value" : 48.763519
    },
    {
      "Date": 20200623, 
      "Value" : 48.763519
    },
    {
      "Date": 20200622, 
      "Value" : 48.763519
    },
    {
      "Date": 20200619, 
      "Value" : 48.763519
    },
    {
      "Date": 20200618, 
      "Value" : 48.763519
    },
    {
      "Date": 20200617, 
      "Value" : 48.763519
    },
    {
      "Date": 20200616, 
      "Value" : 48.763519
    },
    {
      "Date": 20200615, 
      "Value" : 48.763519
    },
    {
      "Date": 20200612, 
      "Value" : 48.763519
    },
    {
      "Date": 20200611, 
      "Value" : 48.763519
    },
    {
      "Date": 20200610, 
      "Value" : 48.763519
    },
    {
      "Date": 20200609, 
      "Value" : 48.763519
    },
    {
      "Date": 20200608, 
      "Value" : 48.763519
    },
    {
      "Date": 20200605, 
      "Value" : 48.763519
    },
    {
      "Date": 20200604, 
      "Value" : 48.763519
    },
    {
      "Date": 20200603, 
      "Value" : 48.763519
    },
    {
      "Date": 20200602, 
      "Value" : 48.763519
    },
    {
      "Date": 20200601, 
      "Value" : 48.763519
    },
    {
      "Date": 20200529, 
      "Value" : 48.763519
    },
    {
      "Date": 20200528, 
      "Value" : 48.763519
    },
    {
      "Date": 20200527, 
      "Value" : 48.763519
    },
    {
      "Date": 20200526, 
      "Value" : 48.763519
    },
    {
      "Date": 20200525, 
      "Value" : 48.763519
    },
    {
      "Date": 20200522, 
      "Value" : 48.763519
    },
    {
      "Date": 20200521, 
      "Value" : 48.763519
    },
    {
      "Date": 20200520, 
      "Value" : 48.763519
    },
    {
      "Date": 20200519, 
      "Value" : 48.763519
    },
    {
      "Date": 20200518, 
      "Value" : 48.763519
    },
    {
      "Date": 20200515, 
      "Value" : 48.763519
    },
    {
      "Date": 20200514, 
      "Value" : 48.763519
    },
    {
      "Date": 20200513, 
      "Value" : 48.763519
    },
    {
      "Date": 20200512, 
      "Value" : 48.763519
    },
    {
      "Date": 20200511, 
      "Value" : 48.763519
    },
    {
      "Date": 20200508, 
      "Value" : 48.763519
    },
    {
      "Date": 20200507, 
      "Value" : 48.763519
    },
    {
      "Date": 20200506, 
      "Value" : 48.763519
    },
    {
      "Date": 20200430, 
      "Value" : 48.763519
    },
    {
      "Date": 20200429, 
      "Value" : 48.763519
    },
    {
      "Date": 20200428, 
      "Value" : 48.763519
    },
    {
      "Date": 20200427, 
      "Value" : 48.763519
    },
    {
      "Date": 20200424, 
      "Value" : 48.763519
    },
    {
      "Date": 20200423, 
      "Value" : 48.763519
    },
    {
      "Date": 20200422, 
      "Value" : 48.763519
    },
    {
      "Date": 20200421, 
      "Value" : 48.763519
    },
    {
      "Date": 20200420, 
      "Value" : 48.763519
    },
    {
      "Date": 20200417, 
      "Value" : 48.763519
    },
    {
      "Date": 20200416, 
      "Value" : 48.763519
    },
    {
      "Date": 20200415, 
      "Value" : 48.763519
    },
    {
      "Date": 20200414, 
      "Value" : 48.763519
    },
    {
      "Date": 20200413, 
      "Value" : 48.763519
    },
    {
      "Date": 20200410, 
      "Value" : 48.763519
    },
    {
      "Date": 20200409, 
      "Value" : 48.763519
    },
    {
      "Date": 20200408, 
      "Value" : 48.763519
    },
    {
      "Date": 20200407, 
      "Value" : 48.763519
    },
    {
      "Date": 20200403, 
      "Value" : 48.763519
    },
    {
      "Date": 20200403, 
      "Value" : 51.003815
    },
    {
      "Date": 20200403, 
      "Value" : -1.000000
    }
  ]
}